{"trackedEntityInstances":[{"orgUnit":"tA562BRGbWF","trackedEntityType":"EL3fkeMR3xK","inactive":false,"deleted":false,"featureType":"NONE","programOwners":[],"enrollments":[{"orgUnit":"tA562BRGbWF","program":"gPWs4FRX9dj","enrollmentDate":"2021-01-01","incidentDate":"2021-01-01","events":[]}],"relationships":[],"attributes":[{"code":"WHO_001","displayName":"Mã BHYT","attribute":"JHb1hzseNMg","value":"HT3378999005809"},{"code":"WHO_002","displayName":"Họ và tên","attribute":"xBoLC0aruyJ","value":"HOÀNG TIẾN DŨNG"},{"code":"WHO_003","displayName":"Giới tính","attribute":"rwreLO34Xg7","value":"01"},{"code":"WHO_004","displayName":"Năm sinh","attribute":"C7USC9MC8yH","value":"1952-01-01"},{"displayName":"Số CMT/CCCD","attribute":"ZQ93P672wQR","value":""},{"displayName":"Số điện thoại","attribute":"mZbgWADLTKY","value":""},{"code":"WHO_005","displayName":"Địa chỉ","attribute":"Bxp1Lhr8ZeN","value":""},{"code":"WHO_006","displayName":"Nghề nghiệp","attribute":"L4djJU4gMyb","value":""}]},{"orgUnit":"SpoPAZdJirm","trackedEntityType":"EL3fkeMR3xK","inactive":false,"deleted":false,"featureType":"NONE","programOwners":[],"enrollments":[{"orgUnit":"SpoPAZdJirm","program":"gPWs4FRX9dj","enrollmentDate":"2021-01-01","incidentDate":"2021-01-01","events":[]}],"relationships":[],"attributes":[{"code":"WHO_001","displayName":"Mã BHYT","attribute":"JHb1hzseNMg","value":"CB2373720080458"},{"code":"WHO_002","displayName":"Họ và tên","attribute":"xBoLC0aruyJ","value":"MAI ANH TUẤN"},{"code":"WHO_003","displayName":"Giới tính","attribute":"rwreLO34Xg7","value":"01"},{"code":"WHO_004","displayName":"Năm sinh","attribute":"C7USC9MC8yH","value":"1957-01-01"},{"displayName":"Số CMT/CCCD","attribute":"ZQ93P672wQR","value":""},{"displayName":"Số điện thoại","attribute":"mZbgWADLTKY","value":""},{"code":"WHO_005","displayName":"Địa chỉ","attribute":"Bxp1Lhr8ZeN","value":""},{"code":"WHO_006","displayName":"Nghề nghiệp","attribute":"L4djJU4gMyb","value":""}]},{"orgUnit":"zwslFumJCg2","trackedEntityType":"EL3fkeMR3xK","inactive":false,"deleted":false,"featureType":"NONE","programOwners":[],"enrollments":[{"orgUnit":"zwslFumJCg2","program":"gPWs4FRX9dj","enrollmentDate":"2021-01-01","incidentDate":"2021-01-01","events":[]}],"relationships":[],"attributes":[{"code":"WHO_001","displayName":"Mã BHYT","attribute":"JHb1hzseNMg","value":"CB2373720957127"},{"code":"WHO_002","displayName":"Họ và tên","attribute":"xBoLC0aruyJ","value":"NGUYỄN TỬ NHU"},{"code":"WHO_003","displayName":"Giới tính","attribute":"rwreLO34Xg7","value":"01"},{"code":"WHO_004","displayName":"Năm sinh","attribute":"C7USC9MC8yH","value":"1956-01-01"},{"displayName":"Số CMT/CCCD","attribute":"ZQ93P672wQR","value":""},{"displayName":"Số điện thoại","attribute":"mZbgWADLTKY","value":""},{"code":"WHO_005","displayName":"Địa chỉ","attribute":"Bxp1Lhr8ZeN","value":""},{"code":"WHO_006","displayName":"Nghề nghiệp","attribute":"L4djJU4gMyb","value":""}]},{"orgUnit":"pfeCqgBS4Zb","trackedEntityType":"EL3fkeMR3xK","inactive":false,"deleted":false,"featureType":"NONE","programOwners":[],"enrollments":[{"orgUnit":"pfeCqgBS4Zb","program":"gPWs4FRX9dj","enrollmentDate":"2021-01-01","incidentDate":"2021-01-01","events":[]}],"relationships":[],"attributes":[{"code":"WHO_001","displayName":"Mã BHYT","attribute":"JHb1hzseNMg","value":"HT3372896023348"},{"code":"WHO_002","displayName":"Họ và tên","attribute":"xBoLC0aruyJ","value":"Hoàng Trung Sơn"},{"code":"WHO_003","displayName":"Giới tính","attribute":"rwreLO34Xg7","value":"01"},{"code":"WHO_004","displayName":"Năm sinh","attribute":"C7USC9MC8yH","value":"1949-01-01"},{"displayName":"Số CMT/CCCD","attribute":"ZQ93P672wQR","value":""},{"displayName":"Số điện thoại","attribute":"mZbgWADLTKY","value":""},{"code":"WHO_005","displayName":"Địa chỉ","attribute":"Bxp1Lhr8ZeN","value":""},{"code":"WHO_006","displayName":"Nghề nghiệp","attribute":"L4djJU4gMyb","value":""}]},{"orgUnit":"t7cn9nU8Ait","trackedEntityType":"EL3fkeMR3xK","inactive":false,"deleted":false,"featureType":"NONE","programOwners":[],"enrollments":[{"orgUnit":"t7cn9nU8Ait","program":"gPWs4FRX9dj","enrollmentDate":"2021-01-01","incidentDate":"2021-01-01","events":[]}],"relationships":[],"attributes":[{"code":"WHO_001","displayName":"Mã BHYT","attribute":"JHb1hzseNMg","value":"TS2373720061380"},{"code":"WHO_002","displayName":"Họ và tên","attribute":"xBoLC0aruyJ","value":"Đinh Thị Minh"},{"code":"WHO_003","displayName":"Giới tính","attribute":"rwreLO34Xg7","value":"02"},{"code":"WHO_004","displayName":"Năm sinh","attribute":"C7USC9MC8yH","value":"1933-01-01"},{"displayName":"Số CMT/CCCD","attribute":"ZQ93P672wQR","value":""},{"displayName":"Số điện thoại","attribute":"mZbgWADLTKY","value":""},{"code":"WHO_005","displayName":"Địa chỉ","attribute":"Bxp1Lhr8ZeN","value":""},{"code":"WHO_006","displayName":"Nghề nghiệp","attribute":"L4djJU4gMyb","value":""}]},{"orgUnit":"t7cn9nU8Ait","trackedEntityType":"EL3fkeMR3xK","inactive":false,"deleted":false,"featureType":"NONE","programOwners":[],"enrollments":[{"orgUnit":"t7cn9nU8Ait","program":"gPWs4FRX9dj","enrollmentDate":"2021-01-01","incidentDate":"2021-01-01","events":[]}],"relationships":[],"attributes":[{"code":"WHO_001","displayName":"Mã BHYT","attribute":"JHb1hzseNMg","value":"CK2373720111784"},{"code":"WHO_002","displayName":"Họ và tên","attribute":"xBoLC0aruyJ","value":"Trần Trung Thông"},{"code":"WHO_003","displayName":"Giới tính","attribute":"rwreLO34Xg7","value":"01"},{"code":"WHO_004","displayName":"Năm sinh","attribute":"C7USC9MC8yH","value":"1946-01-01"},{"displayName":"Số CMT/CCCD","attribute":"ZQ93P672wQR","value":""},{"displayName":"Số điện thoại","attribute":"mZbgWADLTKY","value":""},{"code":"WHO_005","displayName":"Địa chỉ","attribute":"Bxp1Lhr8ZeN","value":""},{"code":"WHO_006","displayName":"Nghề nghiệp","attribute":"L4djJU4gMyb","value":""}]},{"orgUnit":"jFrv1HerHzk","trackedEntityType":"EL3fkeMR3xK","inactive":false,"deleted":false,"featureType":"NONE","programOwners":[],"enrollments":[{"orgUnit":"jFrv1HerHzk","program":"gPWs4FRX9dj","enrollmentDate":"2021-01-01","incidentDate":"2021-01-01","events":[]}],"relationships":[],"attributes":[{"code":"WHO_001","displayName":"Mã BHYT","attribute":"JHb1hzseNMg","value":"CB2373720051446"},{"code":"WHO_002","displayName":"Họ và tên","attribute":"xBoLC0aruyJ","value":"PHẠM QUANG ĐÀO"},{"code":"WHO_003","displayName":"Giới tính","attribute":"rwreLO34Xg7","value":"01"},{"code":"WHO_004","displayName":"Năm sinh","attribute":"C7USC9MC8yH","value":"1958-05-15"},{"displayName":"Số CMT/CCCD","attribute":"ZQ93P672wQR","value":""},{"displayName":"Số điện thoại","attribute":"mZbgWADLTKY","value":""},{"code":"WHO_005","displayName":"Địa chỉ","attribute":"Bxp1Lhr8ZeN","value":""},{"code":"WHO_006","displayName":"Nghề nghiệp","attribute":"L4djJU4gMyb","value":""}]},{"orgUnit":"F7qFecFZ7Ry","trackedEntityType":"EL3fkeMR3xK","inactive":false,"deleted":false,"featureType":"NONE","programOwners":[],"enrollments":[{"orgUnit":"F7qFecFZ7Ry","program":"gPWs4FRX9dj","enrollmentDate":"2021-01-01","incidentDate":"2021-01-01","events":[]}],"relationships":[],"attributes":[{"code":"WHO_001","displayName":"Mã BHYT","attribute":"JHb1hzseNMg","value":"BT2373721026268"},{"code":"WHO_002","displayName":"Họ và tên","attribute":"xBoLC0aruyJ","value":"PHAN VĂN PHÒNG"},{"code":"WHO_003","displayName":"Giới tính","attribute":"rwreLO34Xg7","value":"01"},{"code":"WHO_004","displayName":"Năm sinh","attribute":"C7USC9MC8yH","value":"1975-02-01"},{"displayName":"Số CMT/CCCD","attribute":"ZQ93P672wQR","value":""},{"displayName":"Số điện thoại","attribute":"mZbgWADLTKY","value":""},{"code":"WHO_005","displayName":"Địa chỉ","attribute":"Bxp1Lhr8ZeN","value":""},{"code":"WHO_006","displayName":"Nghề nghiệp","attribute":"L4djJU4gMyb","value":""}]},{"orgUnit":"jZTsDHzsEmT","trackedEntityType":"EL3fkeMR3xK","inactive":false,"deleted":false,"featureType":"NONE","programOwners":[],"enrollments":[{"orgUnit":"jZTsDHzsEmT","program":"gPWs4FRX9dj","enrollmentDate":"2021-01-01","incidentDate":"2021-01-01","events":[]}],"relationships":[],"attributes":[{"code":"WHO_001","displayName":"Mã BHYT","attribute":"JHb1hzseNMg","value":"CK2373720440208"},{"code":"WHO_002","displayName":"Họ và tên","attribute":"xBoLC0aruyJ","value":"NGUYỄN ĐỨC DỊNH"},{"code":"WHO_003","displayName":"Giới tính","attribute":"rwreLO34Xg7","value":"01"},{"code":"WHO_004","displayName":"Năm sinh","attribute":"C7USC9MC8yH","value":"1942-01-01"},{"displayName":"Số CMT/CCCD","attribute":"ZQ93P672wQR","value":""},{"displayName":"Số điện thoại","attribute":"mZbgWADLTKY","value":""},{"code":"WHO_005","displayName":"Địa chỉ","attribute":"Bxp1Lhr8ZeN","value":""},{"code":"WHO_006","displayName":"Nghề nghiệp","attribute":"L4djJU4gMyb","value":""}]},{"orgUnit":"tA562BRGbWF","trackedEntityType":"EL3fkeMR3xK","inactive":false,"deleted":false,"featureType":"NONE","programOwners":[],"enrollments":[{"orgUnit":"tA562BRGbWF","program":"gPWs4FRX9dj","enrollmentDate":"2021-01-01","incidentDate":"2021-01-01","events":[]}],"relationships":[],"attributes":[{"code":"WHO_001","displayName":"Mã BHYT","attribute":"JHb1hzseNMg","value":"HT2373720039094"},{"code":"WHO_002","displayName":"Họ và tên","attribute":"xBoLC0aruyJ","value":"PHẠM HỒNG VANG"},{"code":"WHO_003","displayName":"Giới tính","attribute":"rwreLO34Xg7","value":"01"},{"code":"WHO_004","displayName":"Năm sinh","attribute":"C7USC9MC8yH","value":"1945-01-01"},{"displayName":"Số CMT/CCCD","attribute":"ZQ93P672wQR","value":""},{"displayName":"Số điện thoại","attribute":"mZbgWADLTKY","value":""},{"code":"WHO_005","displayName":"Địa chỉ","attribute":"Bxp1Lhr8ZeN","value":""},{"code":"WHO_006","displayName":"Nghề nghiệp","attribute":"L4djJU4gMyb","value":""}]},{"orgUnit":"XEcvCIDdoUZ","trackedEntityType":"EL3fkeMR3xK","inactive":false,"deleted":false,"featureType":"NONE","programOwners":[],"enrollments":[{"orgUnit":"XEcvCIDdoUZ","program":"gPWs4FRX9dj","enrollmentDate":"2021-01-01","incidentDate":"2021-01-01","events":[]}],"relationships":[],"attributes":[{"code":"WHO_001","displayName":"Mã BHYT","attribute":"JHb1hzseNMg","value":"BT2373720076648"},{"code":"WHO_002","displayName":"Họ và tên","attribute":"xBoLC0aruyJ","value":"LÊ THỊ DUYÊN"},{"code":"WHO_003","displayName":"Giới tính","attribute":"rwreLO34Xg7","value":"02"},{"code":"WHO_004","displayName":"Năm sinh","attribute":"C7USC9MC8yH","value":"1983-01-01"},{"displayName":"Số CMT/CCCD","attribute":"ZQ93P672wQR","value":""},{"displayName":"Số điện thoại","attribute":"mZbgWADLTKY","value":""},{"code":"WHO_005","displayName":"Địa chỉ","attribute":"Bxp1Lhr8ZeN","value":""},{"code":"WHO_006","displayName":"Nghề nghiệp","attribute":"L4djJU4gMyb","value":""}]},{"orgUnit":"Qm1BytbwrhI","trackedEntityType":"EL3fkeMR3xK","inactive":false,"deleted":false,"featureType":"NONE","programOwners":[],"enrollments":[{"orgUnit":"Qm1BytbwrhI","program":"gPWs4FRX9dj","enrollmentDate":"2021-01-01","incidentDate":"2021-01-01","events":[]}],"relationships":[],"attributes":[{"code":"WHO_001","displayName":"Mã BHYT","attribute":"JHb1hzseNMg","value":"HT2373721006475"},{"code":"WHO_002","displayName":"Họ và tên","attribute":"xBoLC0aruyJ","value":"HOÀNG THỊ THỮNG"},{"code":"WHO_003","displayName":"Giới tính","attribute":"rwreLO34Xg7","value":"02"},{"code":"WHO_004","displayName":"Năm sinh","attribute":"C7USC9MC8yH","value":"1946-01-01"},{"displayName":"Số CMT/CCCD","attribute":"ZQ93P672wQR","value":""},{"displayName":"Số điện thoại","attribute":"mZbgWADLTKY","value":""},{"code":"WHO_005","displayName":"Địa chỉ","attribute":"Bxp1Lhr8ZeN","value":""},{"code":"WHO_006","displayName":"Nghề nghiệp","attribute":"L4djJU4gMyb","value":""}]},{"orgUnit":"Qm1BytbwrhI","trackedEntityType":"EL3fkeMR3xK","inactive":false,"deleted":false,"featureType":"NONE","programOwners":[],"enrollments":[{"orgUnit":"Qm1BytbwrhI","program":"gPWs4FRX9dj","enrollmentDate":"2021-01-01","incidentDate":"2021-01-01","events":[]}],"relationships":[],"attributes":[{"code":"WHO_001","displayName":"Mã BHYT","attribute":"JHb1hzseNMg","value":"HT2373721006474"},{"code":"WHO_002","displayName":"Họ và tên","attribute":"xBoLC0aruyJ","value":"HOÀNG NGỌC THÀNH"},{"code":"WHO_003","displayName":"Giới tính","attribute":"rwreLO34Xg7","value":"01"},{"code":"WHO_004","displayName":"Năm sinh","attribute":"C7USC9MC8yH","value":"1945-01-01"},{"displayName":"Số CMT/CCCD","attribute":"ZQ93P672wQR","value":""},{"displayName":"Số điện thoại","attribute":"mZbgWADLTKY","value":""},{"code":"WHO_005","displayName":"Địa chỉ","attribute":"Bxp1Lhr8ZeN","value":""},{"code":"WHO_006","displayName":"Nghề nghiệp","attribute":"L4djJU4gMyb","value":""}]},{"orgUnit":"tA562BRGbWF","trackedEntityType":"EL3fkeMR3xK","inactive":false,"deleted":false,"featureType":"NONE","programOwners":[],"enrollments":[{"orgUnit":"tA562BRGbWF","program":"gPWs4FRX9dj","enrollmentDate":"2021-01-01","incidentDate":"2021-01-01","events":[]}],"relationships":[],"attributes":[{"code":"WHO_001","displayName":"Mã BHYT","attribute":"JHb1hzseNMg","value":"HT2373720050066"},{"code":"WHO_002","displayName":"Họ và tên","attribute":"xBoLC0aruyJ","value":"Phạm Đăng Doanh"},{"code":"WHO_003","displayName":"Giới tính","attribute":"rwreLO34Xg7","value":"01"},{"code":"WHO_004","displayName":"Năm sinh","attribute":"C7USC9MC8yH","value":"1946-01-01"},{"displayName":"Số CMT/CCCD","attribute":"ZQ93P672wQR","value":""},{"displayName":"Số điện thoại","attribute":"mZbgWADLTKY","value":""},{"code":"WHO_005","displayName":"Địa chỉ","attribute":"Bxp1Lhr8ZeN","value":""},{"code":"WHO_006","displayName":"Nghề nghiệp","attribute":"L4djJU4gMyb","value":""}]},{"orgUnit":"BAqlaZeQ8C3","trackedEntityType":"EL3fkeMR3xK","inactive":false,"deleted":false,"featureType":"NONE","programOwners":[],"enrollments":[{"orgUnit":"BAqlaZeQ8C3","program":"gPWs4FRX9dj","enrollmentDate":"2021-01-01","incidentDate":"2021-01-01","events":[]}],"relationships":[],"attributes":[{"code":"WHO_001","displayName":"Mã BHYT","attribute":"JHb1hzseNMg","value":"CB2373720606902"},{"code":"WHO_002","displayName":"Họ và tên","attribute":"xBoLC0aruyJ","value":"ĐINH VĂN CẢNH"},{"code":"WHO_003","displayName":"Giới tính","attribute":"rwreLO34Xg7","value":"01"},{"code":"WHO_004","displayName":"Năm sinh","attribute":"C7USC9MC8yH","value":"1962-10-01"},{"displayName":"Số CMT/CCCD","attribute":"ZQ93P672wQR","value":""},{"displayName":"Số điện thoại","attribute":"mZbgWADLTKY","value":""},{"code":"WHO_005","displayName":"Địa chỉ","attribute":"Bxp1Lhr8ZeN","value":""},{"code":"WHO_006","displayName":"Nghề nghiệp","attribute":"L4djJU4gMyb","value":""}]},{"orgUnit":"Z39aZnXP2tU","trackedEntityType":"EL3fkeMR3xK","inactive":false,"deleted":false,"featureType":"NONE","programOwners":[],"enrollments":[{"orgUnit":"Z39aZnXP2tU","program":"gPWs4FRX9dj","enrollmentDate":"2021-01-01","incidentDate":"2021-01-01","events":[]}],"relationships":[],"attributes":[{"code":"WHO_001","displayName":"Mã BHYT","attribute":"JHb1hzseNMg","value":"HT3373720080023"},{"code":"WHO_002","displayName":"Họ và tên","attribute":"xBoLC0aruyJ","value":"LÊ TRUNG BÌNH"},{"code":"WHO_003","displayName":"Giới tính","attribute":"rwreLO34Xg7","value":"01"},{"code":"WHO_004","displayName":"Năm sinh","attribute":"C7USC9MC8yH","value":"1956-01-01"},{"displayName":"Số CMT/CCCD","attribute":"ZQ93P672wQR","value":""},{"displayName":"Số điện thoại","attribute":"mZbgWADLTKY","value":""},{"code":"WHO_005","displayName":"Địa chỉ","attribute":"Bxp1Lhr8ZeN","value":""},{"code":"WHO_006","displayName":"Nghề nghiệp","attribute":"L4djJU4gMyb","value":""}]},{"orgUnit":"Z39aZnXP2tU","trackedEntityType":"EL3fkeMR3xK","inactive":false,"deleted":false,"featureType":"NONE","programOwners":[],"enrollments":[{"orgUnit":"Z39aZnXP2tU","program":"gPWs4FRX9dj","enrollmentDate":"2021-01-01","incidentDate":"2021-01-01","events":[]}],"relationships":[],"attributes":[{"code":"WHO_001","displayName":"Mã BHYT","attribute":"JHb1hzseNMg","value":"CK2373720051823"},{"code":"WHO_002","displayName":"Họ và tên","attribute":"xBoLC0aruyJ","value":"Trần Thu Chung"},{"code":"WHO_003","displayName":"Giới tính","attribute":"rwreLO34Xg7","value":"01"},{"code":"WHO_004","displayName":"Năm sinh","attribute":"C7USC9MC8yH","value":"1949-01-01"},{"displayName":"Số CMT/CCCD","attribute":"ZQ93P672wQR","value":""},{"displayName":"Số điện thoại","attribute":"mZbgWADLTKY","value":""},{"code":"WHO_005","displayName":"Địa chỉ","attribute":"Bxp1Lhr8ZeN","value":""},{"code":"WHO_006","displayName":"Nghề nghiệp","attribute":"L4djJU4gMyb","value":""}]},{"orgUnit":"Qm1BytbwrhI","trackedEntityType":"EL3fkeMR3xK","inactive":false,"deleted":false,"featureType":"NONE","programOwners":[],"enrollments":[{"orgUnit":"Qm1BytbwrhI","program":"gPWs4FRX9dj","enrollmentDate":"2021-01-01","incidentDate":"2021-01-01","events":[]}],"relationships":[],"attributes":[{"code":"WHO_001","displayName":"Mã BHYT","attribute":"JHb1hzseNMg","value":"CB2373720009233"},{"code":"WHO_002","displayName":"Họ và tên","attribute":"xBoLC0aruyJ","value":"NGUYỄN VĂN THỤ"},{"code":"WHO_003","displayName":"Giới tính","attribute":"rwreLO34Xg7","value":"01"},{"code":"WHO_004","displayName":"Năm sinh","attribute":"C7USC9MC8yH","value":"1957-08-12"},{"displayName":"Số CMT/CCCD","attribute":"ZQ93P672wQR","value":""},{"displayName":"Số điện thoại","attribute":"mZbgWADLTKY","value":""},{"code":"WHO_005","displayName":"Địa chỉ","attribute":"Bxp1Lhr8ZeN","value":""},{"code":"WHO_006","displayName":"Nghề nghiệp","attribute":"L4djJU4gMyb","value":""}]},{"orgUnit":"k0zpQPaobzC","trackedEntityType":"EL3fkeMR3xK","inactive":false,"deleted":false,"featureType":"NONE","programOwners":[],"enrollments":[{"orgUnit":"k0zpQPaobzC","program":"gPWs4FRX9dj","enrollmentDate":"2021-01-01","incidentDate":"2021-01-01","events":[]}],"relationships":[],"attributes":[{"code":"WHO_001","displayName":"Mã BHYT","attribute":"JHb1hzseNMg","value":"BT2373720670822"},{"code":"WHO_002","displayName":"Họ và tên","attribute":"xBoLC0aruyJ","value":"ĐINH VĂN LUẬT"},{"code":"WHO_003","displayName":"Giới tính","attribute":"rwreLO34Xg7","value":"01"},{"code":"WHO_004","displayName":"Năm sinh","attribute":"C7USC9MC8yH","value":"1945-03-20"},{"displayName":"Số CMT/CCCD","attribute":"ZQ93P672wQR","value":""},{"displayName":"Số điện thoại","attribute":"mZbgWADLTKY","value":""},{"code":"WHO_005","displayName":"Địa chỉ","attribute":"Bxp1Lhr8ZeN","value":""},{"code":"WHO_006","displayName":"Nghề nghiệp","attribute":"L4djJU4gMyb","value":""}]},{"orgUnit":"Qm1BytbwrhI","trackedEntityType":"EL3fkeMR3xK","inactive":false,"deleted":false,"featureType":"NONE","programOwners":[],"enrollments":[{"orgUnit":"Qm1BytbwrhI","program":"gPWs4FRX9dj","enrollmentDate":"2021-01-01","incidentDate":"2021-01-01","events":[]}],"relationships":[],"attributes":[{"code":"WHO_001","displayName":"Mã BHYT","attribute":"JHb1hzseNMg","value":"HT3373720080095"},{"code":"WHO_002","displayName":"Họ và tên","attribute":"xBoLC0aruyJ","value":"PHẠM THỊ QUÝ"},{"code":"WHO_003","displayName":"Giới tính","attribute":"rwreLO34Xg7","value":"02"},{"code":"WHO_004","displayName":"Năm sinh","attribute":"C7USC9MC8yH","value":"1954-01-01"},{"displayName":"Số CMT/CCCD","attribute":"ZQ93P672wQR","value":""},{"displayName":"Số điện thoại","attribute":"mZbgWADLTKY","value":""},{"code":"WHO_005","displayName":"Địa chỉ","attribute":"Bxp1Lhr8ZeN","value":""},{"code":"WHO_006","displayName":"Nghề nghiệp","attribute":"L4djJU4gMyb","value":""}]},{"orgUnit":"xmPhbRY70y9","trackedEntityType":"EL3fkeMR3xK","inactive":false,"deleted":false,"featureType":"NONE","programOwners":[],"enrollments":[{"orgUnit":"xmPhbRY70y9","program":"gPWs4FRX9dj","enrollmentDate":"2021-01-01","incidentDate":"2021-01-01","events":[]}],"relationships":[],"attributes":[{"code":"WHO_001","displayName":"Mã BHYT","attribute":"JHb1hzseNMg","value":"TQ4979731392310"},{"code":"WHO_002","displayName":"Họ và tên","attribute":"xBoLC0aruyJ","value":"TRẦN QUANG SÁNG"},{"code":"WHO_003","displayName":"Giới tính","attribute":"rwreLO34Xg7","value":"01"},{"code":"WHO_004","displayName":"Năm sinh","attribute":"C7USC9MC8yH","value":"1957-05-24"},{"displayName":"Số CMT/CCCD","attribute":"ZQ93P672wQR","value":""},{"displayName":"Số điện thoại","attribute":"mZbgWADLTKY","value":""},{"code":"WHO_005","displayName":"Địa chỉ","attribute":"Bxp1Lhr8ZeN","value":""},{"code":"WHO_006","displayName":"Nghề nghiệp","attribute":"L4djJU4gMyb","value":""}]},{"orgUnit":"zwslFumJCg2","trackedEntityType":"EL3fkeMR3xK","inactive":false,"deleted":false,"featureType":"NONE","programOwners":[],"enrollments":[{"orgUnit":"zwslFumJCg2","program":"gPWs4FRX9dj","enrollmentDate":"2021-01-01","incidentDate":"2021-01-01","events":[]}],"relationships":[],"attributes":[{"code":"WHO_001","displayName":"Mã BHYT","attribute":"JHb1hzseNMg","value":"CT2373721015742"},{"code":"WHO_002","displayName":"Họ và tên","attribute":"xBoLC0aruyJ","value":"NGUYỄN THỊ HƯỜNG"},{"code":"WHO_003","displayName":"Giới tính","attribute":"rwreLO34Xg7","value":"02"},{"code":"WHO_004","displayName":"Năm sinh","attribute":"C7USC9MC8yH","value":"1934-01-01"},{"displayName":"Số CMT/CCCD","attribute":"ZQ93P672wQR","value":""},{"displayName":"Số điện thoại","attribute":"mZbgWADLTKY","value":""},{"code":"WHO_005","displayName":"Địa chỉ","attribute":"Bxp1Lhr8ZeN","value":""},{"code":"WHO_006","displayName":"Nghề nghiệp","attribute":"L4djJU4gMyb","value":""}]},{"orgUnit":"xmPhbRY70y9","trackedEntityType":"EL3fkeMR3xK","inactive":false,"deleted":false,"featureType":"NONE","programOwners":[],"enrollments":[{"orgUnit":"xmPhbRY70y9","program":"gPWs4FRX9dj","enrollmentDate":"2021-01-01","incidentDate":"2021-01-01","events":[]}],"relationships":[],"attributes":[{"code":"WHO_001","displayName":"Mã BHYT","attribute":"JHb1hzseNMg","value":"HT3372896008607"},{"code":"WHO_002","displayName":"Họ và tên","attribute":"xBoLC0aruyJ","value":"Đinh Lương Dân"},{"code":"WHO_003","displayName":"Giới tính","attribute":"rwreLO34Xg7","value":"01"},{"code":"WHO_004","displayName":"Năm sinh","attribute":"C7USC9MC8yH","value":"1955-01-01"},{"displayName":"Số CMT/CCCD","attribute":"ZQ93P672wQR","value":""},{"displayName":"Số điện thoại","attribute":"mZbgWADLTKY","value":""},{"code":"WHO_005","displayName":"Địa chỉ","attribute":"Bxp1Lhr8ZeN","value":""},{"code":"WHO_006","displayName":"Nghề nghiệp","attribute":"L4djJU4gMyb","value":""}]},{"orgUnit":"DaMOC6ucylB","trackedEntityType":"EL3fkeMR3xK","inactive":false,"deleted":false,"featureType":"NONE","programOwners":[],"enrollments":[{"orgUnit":"DaMOC6ucylB","program":"gPWs4FRX9dj","enrollmentDate":"2021-01-01","incidentDate":"2021-01-01","events":[]}],"relationships":[],"attributes":[{"code":"WHO_001","displayName":"Mã BHYT","attribute":"JHb1hzseNMg","value":"BT2373720212878"},{"code":"WHO_002","displayName":"Họ và tên","attribute":"xBoLC0aruyJ","value":"NGUYỄN VĂN TRƯỜNG"},{"code":"WHO_003","displayName":"Giới tính","attribute":"rwreLO34Xg7","value":"01"},{"code":"WHO_004","displayName":"Năm sinh","attribute":"C7USC9MC8yH","value":"1977-08-01"},{"displayName":"Số CMT/CCCD","attribute":"ZQ93P672wQR","value":""},{"displayName":"Số điện thoại","attribute":"mZbgWADLTKY","value":""},{"code":"WHO_005","displayName":"Địa chỉ","attribute":"Bxp1Lhr8ZeN","value":""},{"code":"WHO_006","displayName":"Nghề nghiệp","attribute":"L4djJU4gMyb","value":""}]},{"orgUnit":"eDrHvC5zZEW","trackedEntityType":"EL3fkeMR3xK","inactive":false,"deleted":false,"featureType":"NONE","programOwners":[],"enrollments":[{"orgUnit":"eDrHvC5zZEW","program":"gPWs4FRX9dj","enrollmentDate":"2021-01-01","incidentDate":"2021-01-01","events":[]}],"relationships":[],"attributes":[{"code":"WHO_001","displayName":"Mã BHYT","attribute":"JHb1hzseNMg","value":"CB2373720056741"},{"code":"WHO_002","displayName":"Họ và tên","attribute":"xBoLC0aruyJ","value":"Hoàng Văn Sinh"},{"code":"WHO_003","displayName":"Giới tính","attribute":"rwreLO34Xg7","value":"01"},{"code":"WHO_004","displayName":"Năm sinh","attribute":"C7USC9MC8yH","value":"1958-09-21"},{"displayName":"Số CMT/CCCD","attribute":"ZQ93P672wQR","value":""},{"displayName":"Số điện thoại","attribute":"mZbgWADLTKY","value":""},{"code":"WHO_005","displayName":"Địa chỉ","attribute":"Bxp1Lhr8ZeN","value":""},{"code":"WHO_006","displayName":"Nghề nghiệp","attribute":"L4djJU4gMyb","value":""}]},{"orgUnit":"n1YBaV10Wlz","trackedEntityType":"EL3fkeMR3xK","inactive":false,"deleted":false,"featureType":"NONE","programOwners":[],"enrollments":[{"orgUnit":"n1YBaV10Wlz","program":"gPWs4FRX9dj","enrollmentDate":"2021-01-01","incidentDate":"2021-01-01","events":[]}],"relationships":[],"attributes":[{"code":"WHO_001","displayName":"Mã BHYT","attribute":"JHb1hzseNMg","value":"BT2373720092957"},{"code":"WHO_002","displayName":"Họ và tên","attribute":"xBoLC0aruyJ","value":"Lê Văn Long"},{"code":"WHO_003","displayName":"Giới tính","attribute":"rwreLO34Xg7","value":"01"},{"code":"WHO_004","displayName":"Năm sinh","attribute":"C7USC9MC8yH","value":"1959-01-01"},{"displayName":"Số CMT/CCCD","attribute":"ZQ93P672wQR","value":""},{"displayName":"Số điện thoại","attribute":"mZbgWADLTKY","value":""},{"code":"WHO_005","displayName":"Địa chỉ","attribute":"Bxp1Lhr8ZeN","value":""},{"code":"WHO_006","displayName":"Nghề nghiệp","attribute":"L4djJU4gMyb","value":""}]},{"orgUnit":"oqNqYhiiPkY","trackedEntityType":"EL3fkeMR3xK","inactive":false,"deleted":false,"featureType":"NONE","programOwners":[],"enrollments":[{"orgUnit":"oqNqYhiiPkY","program":"gPWs4FRX9dj","enrollmentDate":"2021-01-01","incidentDate":"2021-01-01","events":[]}],"relationships":[],"attributes":[{"code":"WHO_001","displayName":"Mã BHYT","attribute":"JHb1hzseNMg","value":"KC4373720468614"},{"code":"WHO_002","displayName":"Họ và tên","attribute":"xBoLC0aruyJ","value":"PHẠM THỊ CHẮT"},{"code":"WHO_003","displayName":"Giới tính","attribute":"rwreLO34Xg7","value":"02"},{"code":"WHO_004","displayName":"Năm sinh","attribute":"C7USC9MC8yH","value":"1949-08-01"},{"displayName":"Số CMT/CCCD","attribute":"ZQ93P672wQR","value":""},{"displayName":"Số điện thoại","attribute":"mZbgWADLTKY","value":""},{"code":"WHO_005","displayName":"Địa chỉ","attribute":"Bxp1Lhr8ZeN","value":""},{"code":"WHO_006","displayName":"Nghề nghiệp","attribute":"L4djJU4gMyb","value":""}]},{"orgUnit":"tA562BRGbWF","trackedEntityType":"EL3fkeMR3xK","inactive":false,"deleted":false,"featureType":"NONE","programOwners":[],"enrollments":[{"orgUnit":"tA562BRGbWF","program":"gPWs4FRX9dj","enrollmentDate":"2021-01-01","incidentDate":"2021-01-01","events":[]}],"relationships":[],"attributes":[{"code":"WHO_001","displayName":"Mã BHYT","attribute":"JHb1hzseNMg","value":"CB2373720019231"},{"code":"WHO_002","displayName":"Họ và tên","attribute":"xBoLC0aruyJ","value":"NGUYỄN NGỌC SƠN"},{"code":"WHO_003","displayName":"Giới tính","attribute":"rwreLO34Xg7","value":"01"},{"code":"WHO_004","displayName":"Năm sinh","attribute":"C7USC9MC8yH","value":"1958-08-06"},{"displayName":"Số CMT/CCCD","attribute":"ZQ93P672wQR","value":""},{"displayName":"Số điện thoại","attribute":"mZbgWADLTKY","value":""},{"code":"WHO_005","displayName":"Địa chỉ","attribute":"Bxp1Lhr8ZeN","value":""},{"code":"WHO_006","displayName":"Nghề nghiệp","attribute":"L4djJU4gMyb","value":""}]},{"orgUnit":"Qm1BytbwrhI","trackedEntityType":"EL3fkeMR3xK","inactive":false,"deleted":false,"featureType":"NONE","programOwners":[],"enrollments":[{"orgUnit":"Qm1BytbwrhI","program":"gPWs4FRX9dj","enrollmentDate":"2021-01-01","incidentDate":"2021-01-01","events":[]}],"relationships":[],"attributes":[{"code":"WHO_001","displayName":"Mã BHYT","attribute":"JHb1hzseNMg","value":"HT2373720092694"},{"code":"WHO_002","displayName":"Họ và tên","attribute":"xBoLC0aruyJ","value":"NGUYỄN VĂN THĂNG"},{"code":"WHO_003","displayName":"Giới tính","attribute":"rwreLO34Xg7","value":"01"},{"code":"WHO_004","displayName":"Năm sinh","attribute":"C7USC9MC8yH","value":"1946-01-01"},{"displayName":"Số CMT/CCCD","attribute":"ZQ93P672wQR","value":""},{"displayName":"Số điện thoại","attribute":"mZbgWADLTKY","value":""},{"code":"WHO_005","displayName":"Địa chỉ","attribute":"Bxp1Lhr8ZeN","value":""},{"code":"WHO_006","displayName":"Nghề nghiệp","attribute":"L4djJU4gMyb","value":""}]},{"orgUnit":"jFrv1HerHzk","trackedEntityType":"EL3fkeMR3xK","inactive":false,"deleted":false,"featureType":"NONE","programOwners":[],"enrollments":[{"orgUnit":"jFrv1HerHzk","program":"gPWs4FRX9dj","enrollmentDate":"2021-01-01","incidentDate":"2021-01-01","events":[]}],"relationships":[],"attributes":[{"code":"WHO_001","displayName":"Mã BHYT","attribute":"JHb1hzseNMg","value":"BT2373721094409"},{"code":"WHO_002","displayName":"Họ và tên","attribute":"xBoLC0aruyJ","value":"NGUYỄN THỊ TỈNH"},{"code":"WHO_003","displayName":"Giới tính","attribute":"rwreLO34Xg7","value":"02"},{"code":"WHO_004","displayName":"Năm sinh","attribute":"C7USC9MC8yH","value":"1930-01-01"},{"displayName":"Số CMT/CCCD","attribute":"ZQ93P672wQR","value":""},{"displayName":"Số điện thoại","attribute":"mZbgWADLTKY","value":""},{"code":"WHO_005","displayName":"Địa chỉ","attribute":"Bxp1Lhr8ZeN","value":""},{"code":"WHO_006","displayName":"Nghề nghiệp","attribute":"L4djJU4gMyb","value":""}]},{"orgUnit":"xmPhbRY70y9","trackedEntityType":"EL3fkeMR3xK","inactive":false,"deleted":false,"featureType":"NONE","programOwners":[],"enrollments":[{"orgUnit":"xmPhbRY70y9","program":"gPWs4FRX9dj","enrollmentDate":"2021-01-01","incidentDate":"2021-01-01","events":[]}],"relationships":[],"attributes":[{"code":"WHO_001","displayName":"Mã BHYT","attribute":"JHb1hzseNMg","value":"HT2372896030183"},{"code":"WHO_002","displayName":"Họ và tên","attribute":"xBoLC0aruyJ","value":"NGUYỄN THÀNH CÔNG"},{"code":"WHO_003","displayName":"Giới tính","attribute":"rwreLO34Xg7","value":"01"},{"code":"WHO_004","displayName":"Năm sinh","attribute":"C7USC9MC8yH","value":"1957-08-13"},{"displayName":"Số CMT/CCCD","attribute":"ZQ93P672wQR","value":""},{"displayName":"Số điện thoại","attribute":"mZbgWADLTKY","value":""},{"code":"WHO_005","displayName":"Địa chỉ","attribute":"Bxp1Lhr8ZeN","value":""},{"code":"WHO_006","displayName":"Nghề nghiệp","attribute":"L4djJU4gMyb","value":""}]},{"orgUnit":"xmPhbRY70y9","trackedEntityType":"EL3fkeMR3xK","inactive":false,"deleted":false,"featureType":"NONE","programOwners":[],"enrollments":[{"orgUnit":"xmPhbRY70y9","program":"gPWs4FRX9dj","enrollmentDate":"2021-01-01","incidentDate":"2021-01-01","events":[]}],"relationships":[],"attributes":[{"code":"WHO_001","displayName":"Mã BHYT","attribute":"JHb1hzseNMg","value":"CB2373720098271"},{"code":"WHO_002","displayName":"Họ và tên","attribute":"xBoLC0aruyJ","value":"PHẠM TÀI KHOẢN"},{"code":"WHO_003","displayName":"Giới tính","attribute":"rwreLO34Xg7","value":"01"},{"code":"WHO_004","displayName":"Năm sinh","attribute":"C7USC9MC8yH","value":"1954-01-01"},{"displayName":"Số CMT/CCCD","attribute":"ZQ93P672wQR","value":""},{"displayName":"Số điện thoại","attribute":"mZbgWADLTKY","value":""},{"code":"WHO_005","displayName":"Địa chỉ","attribute":"Bxp1Lhr8ZeN","value":""},{"code":"WHO_006","displayName":"Nghề nghiệp","attribute":"L4djJU4gMyb","value":""}]},{"orgUnit":"v2Nw9TuueZB","trackedEntityType":"EL3fkeMR3xK","inactive":false,"deleted":false,"featureType":"NONE","programOwners":[],"enrollments":[{"orgUnit":"v2Nw9TuueZB","program":"gPWs4FRX9dj","enrollmentDate":"2021-01-01","incidentDate":"2021-01-01","events":[]}],"relationships":[],"attributes":[{"code":"WHO_001","displayName":"Mã BHYT","attribute":"JHb1hzseNMg","value":"BT2373720393525"},{"code":"WHO_002","displayName":"Họ và tên","attribute":"xBoLC0aruyJ","value":"NGUYỄN THỊ HOÀ"},{"code":"WHO_003","displayName":"Giới tính","attribute":"rwreLO34Xg7","value":"02"},{"code":"WHO_004","displayName":"Năm sinh","attribute":"C7USC9MC8yH","value":"1931-01-01"},{"displayName":"Số CMT/CCCD","attribute":"ZQ93P672wQR","value":""},{"displayName":"Số điện thoại","attribute":"mZbgWADLTKY","value":""},{"code":"WHO_005","displayName":"Địa chỉ","attribute":"Bxp1Lhr8ZeN","value":""},{"code":"WHO_006","displayName":"Nghề nghiệp","attribute":"L4djJU4gMyb","value":""}]},{"orgUnit":"n1YBaV10Wlz","trackedEntityType":"EL3fkeMR3xK","inactive":false,"deleted":false,"featureType":"NONE","programOwners":[],"enrollments":[{"orgUnit":"n1YBaV10Wlz","program":"gPWs4FRX9dj","enrollmentDate":"2021-01-01","incidentDate":"2021-01-01","events":[]}],"relationships":[],"attributes":[{"code":"WHO_001","displayName":"Mã BHYT","attribute":"JHb1hzseNMg","value":"TC3373720112812"},{"code":"WHO_002","displayName":"Họ và tên","attribute":"xBoLC0aruyJ","value":"Trần Thị Chi"},{"code":"WHO_003","displayName":"Giới tính","attribute":"rwreLO34Xg7","value":"02"},{"code":"WHO_004","displayName":"Năm sinh","attribute":"C7USC9MC8yH","value":"1947-01-01"},{"displayName":"Số CMT/CCCD","attribute":"ZQ93P672wQR","value":""},{"displayName":"Số điện thoại","attribute":"mZbgWADLTKY","value":""},{"code":"WHO_005","displayName":"Địa chỉ","attribute":"Bxp1Lhr8ZeN","value":""},{"code":"WHO_006","displayName":"Nghề nghiệp","attribute":"L4djJU4gMyb","value":""}]},{"orgUnit":"oqNqYhiiPkY","trackedEntityType":"EL3fkeMR3xK","inactive":false,"deleted":false,"featureType":"NONE","programOwners":[],"enrollments":[{"orgUnit":"oqNqYhiiPkY","program":"gPWs4FRX9dj","enrollmentDate":"2021-01-01","incidentDate":"2021-01-01","events":[]}],"relationships":[],"attributes":[{"code":"WHO_001","displayName":"Mã BHYT","attribute":"JHb1hzseNMg","value":"HT3372896019781"},{"code":"WHO_002","displayName":"Họ và tên","attribute":"xBoLC0aruyJ","value":"Nguyễn Sỹ Chất"},{"code":"WHO_003","displayName":"Giới tính","attribute":"rwreLO34Xg7","value":"01"},{"code":"WHO_004","displayName":"Năm sinh","attribute":"C7USC9MC8yH","value":"1959-01-02"},{"displayName":"Số CMT/CCCD","attribute":"ZQ93P672wQR","value":""},{"displayName":"Số điện thoại","attribute":"mZbgWADLTKY","value":""},{"code":"WHO_005","displayName":"Địa chỉ","attribute":"Bxp1Lhr8ZeN","value":""},{"code":"WHO_006","displayName":"Nghề nghiệp","attribute":"L4djJU4gMyb","value":""}]},{"orgUnit":"SpoPAZdJirm","trackedEntityType":"EL3fkeMR3xK","inactive":false,"deleted":false,"featureType":"NONE","programOwners":[],"enrollments":[{"orgUnit":"SpoPAZdJirm","program":"gPWs4FRX9dj","enrollmentDate":"2021-01-01","incidentDate":"2021-01-01","events":[]}],"relationships":[],"attributes":[{"code":"WHO_001","displayName":"Mã BHYT","attribute":"JHb1hzseNMg","value":"CB2373721174960"},{"code":"WHO_002","displayName":"Họ và tên","attribute":"xBoLC0aruyJ","value":"VŨ VĂN TÁM"},{"code":"WHO_003","displayName":"Giới tính","attribute":"rwreLO34Xg7","value":"01"},{"code":"WHO_004","displayName":"Năm sinh","attribute":"C7USC9MC8yH","value":"1964-07-10"},{"displayName":"Số CMT/CCCD","attribute":"ZQ93P672wQR","value":""},{"displayName":"Số điện thoại","attribute":"mZbgWADLTKY","value":""},{"code":"WHO_005","displayName":"Địa chỉ","attribute":"Bxp1Lhr8ZeN","value":""},{"code":"WHO_006","displayName":"Nghề nghiệp","attribute":"L4djJU4gMyb","value":""}]},{"orgUnit":"eDrHvC5zZEW","trackedEntityType":"EL3fkeMR3xK","inactive":false,"deleted":false,"featureType":"NONE","programOwners":[],"enrollments":[{"orgUnit":"eDrHvC5zZEW","program":"gPWs4FRX9dj","enrollmentDate":"2021-01-01","incidentDate":"2021-01-01","events":[]}],"relationships":[],"attributes":[{"code":"WHO_001","displayName":"Mã BHYT","attribute":"JHb1hzseNMg","value":"TQ4979731590791"},{"code":"WHO_002","displayName":"Họ và tên","attribute":"xBoLC0aruyJ","value":"PHẠM VĂN TOÀN"},{"code":"WHO_003","displayName":"Giới tính","attribute":"rwreLO34Xg7","value":"01"},{"code":"WHO_004","displayName":"Năm sinh","attribute":"C7USC9MC8yH","value":"1946-01-01"},{"displayName":"Số CMT/CCCD","attribute":"ZQ93P672wQR","value":""},{"displayName":"Số điện thoại","attribute":"mZbgWADLTKY","value":""},{"code":"WHO_005","displayName":"Địa chỉ","attribute":"Bxp1Lhr8ZeN","value":""},{"code":"WHO_006","displayName":"Nghề nghiệp","attribute":"L4djJU4gMyb","value":""}]},{"orgUnit":"jFrv1HerHzk","trackedEntityType":"EL3fkeMR3xK","inactive":false,"deleted":false,"featureType":"NONE","programOwners":[],"enrollments":[{"orgUnit":"jFrv1HerHzk","program":"gPWs4FRX9dj","enrollmentDate":"2021-01-01","incidentDate":"2021-01-01","events":[]}],"relationships":[],"attributes":[{"code":"WHO_001","displayName":"Mã BHYT","attribute":"JHb1hzseNMg","value":"HT3372805002221"},{"code":"WHO_002","displayName":"Họ và tên","attribute":"xBoLC0aruyJ","value":"Nguyễn Văn Hà"},{"code":"WHO_003","displayName":"Giới tính","attribute":"rwreLO34Xg7","value":"01"},{"code":"WHO_004","displayName":"Năm sinh","attribute":"C7USC9MC8yH","value":"1957-01-01"},{"displayName":"Số CMT/CCCD","attribute":"ZQ93P672wQR","value":""},{"displayName":"Số điện thoại","attribute":"mZbgWADLTKY","value":""},{"code":"WHO_005","displayName":"Địa chỉ","attribute":"Bxp1Lhr8ZeN","value":""},{"code":"WHO_006","displayName":"Nghề nghiệp","attribute":"L4djJU4gMyb","value":""}]},{"orgUnit":"jFrv1HerHzk","trackedEntityType":"EL3fkeMR3xK","inactive":false,"deleted":false,"featureType":"NONE","programOwners":[],"enrollments":[{"orgUnit":"jFrv1HerHzk","program":"gPWs4FRX9dj","enrollmentDate":"2021-01-01","incidentDate":"2021-01-01","events":[]}],"relationships":[],"attributes":[{"code":"WHO_001","displayName":"Mã BHYT","attribute":"JHb1hzseNMg","value":"HT2373720068761"},{"code":"WHO_002","displayName":"Họ và tên","attribute":"xBoLC0aruyJ","value":"NGUYỄN TẤN KHUYÊN"},{"code":"WHO_003","displayName":"Giới tính","attribute":"rwreLO34Xg7","value":"01"},{"code":"WHO_004","displayName":"Năm sinh","attribute":"C7USC9MC8yH","value":"1928-01-01"},{"displayName":"Số CMT/CCCD","attribute":"ZQ93P672wQR","value":""},{"displayName":"Số điện thoại","attribute":"mZbgWADLTKY","value":""},{"code":"WHO_005","displayName":"Địa chỉ","attribute":"Bxp1Lhr8ZeN","value":""},{"code":"WHO_006","displayName":"Nghề nghiệp","attribute":"L4djJU4gMyb","value":""}]},{"orgUnit":"SpoPAZdJirm","trackedEntityType":"EL3fkeMR3xK","inactive":false,"deleted":false,"featureType":"NONE","programOwners":[],"enrollments":[{"orgUnit":"SpoPAZdJirm","program":"gPWs4FRX9dj","enrollmentDate":"2021-01-01","incidentDate":"2021-01-01","events":[]}],"relationships":[],"attributes":[{"code":"WHO_001","displayName":"Mã BHYT","attribute":"JHb1hzseNMg","value":"HT3372896026779"},{"code":"WHO_002","displayName":"Họ và tên","attribute":"xBoLC0aruyJ","value":"PHẠM THỊ HÒA"},{"code":"WHO_003","displayName":"Giới tính","attribute":"rwreLO34Xg7","value":"02"},{"code":"WHO_004","displayName":"Năm sinh","attribute":"C7USC9MC8yH","value":"1960-03-03"},{"displayName":"Số CMT/CCCD","attribute":"ZQ93P672wQR","value":""},{"displayName":"Số điện thoại","attribute":"mZbgWADLTKY","value":""},{"code":"WHO_005","displayName":"Địa chỉ","attribute":"Bxp1Lhr8ZeN","value":""},{"code":"WHO_006","displayName":"Nghề nghiệp","attribute":"L4djJU4gMyb","value":""}]},{"orgUnit":"wZvgAlGGu0x","trackedEntityType":"EL3fkeMR3xK","inactive":false,"deleted":false,"featureType":"NONE","programOwners":[],"enrollments":[{"orgUnit":"wZvgAlGGu0x","program":"gPWs4FRX9dj","enrollmentDate":"2021-01-01","incidentDate":"2021-01-01","events":[]}],"relationships":[],"attributes":[{"code":"WHO_001","displayName":"Mã BHYT","attribute":"JHb1hzseNMg","value":"HT3373720121374"},{"code":"WHO_002","displayName":"Họ và tên","attribute":"xBoLC0aruyJ","value":"NGUYỄN THỊ ĐĂNG"},{"code":"WHO_003","displayName":"Giới tính","attribute":"rwreLO34Xg7","value":"02"},{"code":"WHO_004","displayName":"Năm sinh","attribute":"C7USC9MC8yH","value":"1953-01-01"},{"displayName":"Số CMT/CCCD","attribute":"ZQ93P672wQR","value":""},{"displayName":"Số điện thoại","attribute":"mZbgWADLTKY","value":""},{"code":"WHO_005","displayName":"Địa chỉ","attribute":"Bxp1Lhr8ZeN","value":""},{"code":"WHO_006","displayName":"Nghề nghiệp","attribute":"L4djJU4gMyb","value":""}]},{"orgUnit":"v2Nw9TuueZB","trackedEntityType":"EL3fkeMR3xK","inactive":false,"deleted":false,"featureType":"NONE","programOwners":[],"enrollments":[{"orgUnit":"v2Nw9TuueZB","program":"gPWs4FRX9dj","enrollmentDate":"2021-01-01","incidentDate":"2021-01-01","events":[]}],"relationships":[],"attributes":[{"code":"WHO_001","displayName":"Mã BHYT","attribute":"JHb1hzseNMg","value":"CB2373720413653"},{"code":"WHO_002","displayName":"Họ và tên","attribute":"xBoLC0aruyJ","value":"Nguyễn Văn Lực"},{"code":"WHO_003","displayName":"Giới tính","attribute":"rwreLO34Xg7","value":"01"},{"code":"WHO_004","displayName":"Năm sinh","attribute":"C7USC9MC8yH","value":"1963-12-29"},{"displayName":"Số CMT/CCCD","attribute":"ZQ93P672wQR","value":""},{"displayName":"Số điện thoại","attribute":"mZbgWADLTKY","value":""},{"code":"WHO_005","displayName":"Địa chỉ","attribute":"Bxp1Lhr8ZeN","value":""},{"code":"WHO_006","displayName":"Nghề nghiệp","attribute":"L4djJU4gMyb","value":""}]},{"orgUnit":"tA562BRGbWF","trackedEntityType":"EL3fkeMR3xK","inactive":false,"deleted":false,"featureType":"NONE","programOwners":[],"enrollments":[{"orgUnit":"tA562BRGbWF","program":"gPWs4FRX9dj","enrollmentDate":"2021-01-01","incidentDate":"2021-01-01","events":[]}],"relationships":[],"attributes":[{"code":"WHO_001","displayName":"Mã BHYT","attribute":"JHb1hzseNMg","value":"HT2373720061283"},{"code":"WHO_002","displayName":"Họ và tên","attribute":"xBoLC0aruyJ","value":"VŨ ĐÌNH HOẠT"},{"code":"WHO_003","displayName":"Giới tính","attribute":"rwreLO34Xg7","value":"01"},{"code":"WHO_004","displayName":"Năm sinh","attribute":"C7USC9MC8yH","value":"1942-01-01"},{"displayName":"Số CMT/CCCD","attribute":"ZQ93P672wQR","value":""},{"displayName":"Số điện thoại","attribute":"mZbgWADLTKY","value":""},{"code":"WHO_005","displayName":"Địa chỉ","attribute":"Bxp1Lhr8ZeN","value":""},{"code":"WHO_006","displayName":"Nghề nghiệp","attribute":"L4djJU4gMyb","value":""}]},{"orgUnit":"t7cn9nU8Ait","trackedEntityType":"EL3fkeMR3xK","inactive":false,"deleted":false,"featureType":"NONE","programOwners":[],"enrollments":[{"orgUnit":"t7cn9nU8Ait","program":"gPWs4FRX9dj","enrollmentDate":"2021-01-01","incidentDate":"2021-01-01","events":[]}],"relationships":[],"attributes":[{"code":"WHO_001","displayName":"Mã BHYT","attribute":"JHb1hzseNMg","value":"HT2372899032734"},{"code":"WHO_002","displayName":"Họ và tên","attribute":"xBoLC0aruyJ","value":"NGUYỄN VĂN CƯ"},{"code":"WHO_003","displayName":"Giới tính","attribute":"rwreLO34Xg7","value":"01"},{"code":"WHO_004","displayName":"Năm sinh","attribute":"C7USC9MC8yH","value":"1947-01-01"},{"displayName":"Số CMT/CCCD","attribute":"ZQ93P672wQR","value":""},{"displayName":"Số điện thoại","attribute":"mZbgWADLTKY","value":""},{"code":"WHO_005","displayName":"Địa chỉ","attribute":"Bxp1Lhr8ZeN","value":""},{"code":"WHO_006","displayName":"Nghề nghiệp","attribute":"L4djJU4gMyb","value":""}]},{"orgUnit":"Z39aZnXP2tU","trackedEntityType":"EL3fkeMR3xK","inactive":false,"deleted":false,"featureType":"NONE","programOwners":[],"enrollments":[{"orgUnit":"Z39aZnXP2tU","program":"gPWs4FRX9dj","enrollmentDate":"2021-01-01","incidentDate":"2021-01-01","events":[]}],"relationships":[],"attributes":[{"code":"WHO_001","displayName":"Mã BHYT","attribute":"JHb1hzseNMg","value":"CB2373721088038"},{"code":"WHO_002","displayName":"Họ và tên","attribute":"xBoLC0aruyJ","value":"NGUYỄN VĂN THOÀN"},{"code":"WHO_003","displayName":"Giới tính","attribute":"rwreLO34Xg7","value":"01"},{"code":"WHO_004","displayName":"Năm sinh","attribute":"C7USC9MC8yH","value":"1954-09-10"},{"displayName":"Số CMT/CCCD","attribute":"ZQ93P672wQR","value":""},{"displayName":"Số điện thoại","attribute":"mZbgWADLTKY","value":""},{"code":"WHO_005","displayName":"Địa chỉ","attribute":"Bxp1Lhr8ZeN","value":""},{"code":"WHO_006","displayName":"Nghề nghiệp","attribute":"L4djJU4gMyb","value":""}]},{"orgUnit":"xmPhbRY70y9","trackedEntityType":"EL3fkeMR3xK","inactive":false,"deleted":false,"featureType":"NONE","programOwners":[],"enrollments":[{"orgUnit":"xmPhbRY70y9","program":"gPWs4FRX9dj","enrollmentDate":"2021-01-01","incidentDate":"2021-01-01","events":[]}],"relationships":[],"attributes":[{"code":"WHO_001","displayName":"Mã BHYT","attribute":"JHb1hzseNMg","value":"TS2373720036044"},{"code":"WHO_002","displayName":"Họ và tên","attribute":"xBoLC0aruyJ","value":"Vũ Thị Thuận"},{"code":"WHO_003","displayName":"Giới tính","attribute":"rwreLO34Xg7","value":"02"},{"code":"WHO_004","displayName":"Năm sinh","attribute":"C7USC9MC8yH","value":"1959-01-01"},{"displayName":"Số CMT/CCCD","attribute":"ZQ93P672wQR","value":""},{"displayName":"Số điện thoại","attribute":"mZbgWADLTKY","value":""},{"code":"WHO_005","displayName":"Địa chỉ","attribute":"Bxp1Lhr8ZeN","value":""},{"code":"WHO_006","displayName":"Nghề nghiệp","attribute":"L4djJU4gMyb","value":""}]},{"orgUnit":"t7cn9nU8Ait","trackedEntityType":"EL3fkeMR3xK","inactive":false,"deleted":false,"featureType":"NONE","programOwners":[],"enrollments":[{"orgUnit":"t7cn9nU8Ait","program":"gPWs4FRX9dj","enrollmentDate":"2021-01-01","incidentDate":"2021-01-01","events":[]}],"relationships":[],"attributes":[{"code":"WHO_001","displayName":"Mã BHYT","attribute":"JHb1hzseNMg","value":"MS4373721009595"},{"code":"WHO_002","displayName":"Họ và tên","attribute":"xBoLC0aruyJ","value":"Phạm Thị Kim Quyên"},{"code":"WHO_003","displayName":"Giới tính","attribute":"rwreLO34Xg7","value":"02"},{"code":"WHO_004","displayName":"Năm sinh","attribute":"C7USC9MC8yH","value":"1955-01-01"},{"displayName":"Số CMT/CCCD","attribute":"ZQ93P672wQR","value":""},{"displayName":"Số điện thoại","attribute":"mZbgWADLTKY","value":""},{"code":"WHO_005","displayName":"Địa chỉ","attribute":"Bxp1Lhr8ZeN","value":""},{"code":"WHO_006","displayName":"Nghề nghiệp","attribute":"L4djJU4gMyb","value":""}]},{"orgUnit":"t7cn9nU8Ait","trackedEntityType":"EL3fkeMR3xK","inactive":false,"deleted":false,"featureType":"NONE","programOwners":[],"enrollments":[{"orgUnit":"t7cn9nU8Ait","program":"gPWs4FRX9dj","enrollmentDate":"2021-01-01","incidentDate":"2021-01-01","events":[]}],"relationships":[],"attributes":[{"code":"WHO_001","displayName":"Mã BHYT","attribute":"JHb1hzseNMg","value":"XK4373720070079"},{"code":"WHO_002","displayName":"Họ và tên","attribute":"xBoLC0aruyJ","value":"NGUYỄN HỮU KỲ"},{"code":"WHO_003","displayName":"Giới tính","attribute":"rwreLO34Xg7","value":"01"},{"code":"WHO_004","displayName":"Năm sinh","attribute":"C7USC9MC8yH","value":"1959-07-12"},{"displayName":"Số CMT/CCCD","attribute":"ZQ93P672wQR","value":""},{"displayName":"Số điện thoại","attribute":"mZbgWADLTKY","value":""},{"code":"WHO_005","displayName":"Địa chỉ","attribute":"Bxp1Lhr8ZeN","value":""},{"code":"WHO_006","displayName":"Nghề nghiệp","attribute":"L4djJU4gMyb","value":""}]},{"orgUnit":"zsoDje3ItoP","trackedEntityType":"EL3fkeMR3xK","inactive":false,"deleted":false,"featureType":"NONE","programOwners":[],"enrollments":[{"orgUnit":"zsoDje3ItoP","program":"gPWs4FRX9dj","enrollmentDate":"2021-01-01","incidentDate":"2021-01-01","events":[]}],"relationships":[],"attributes":[{"code":"WHO_001","displayName":"Mã BHYT","attribute":"JHb1hzseNMg","value":"HT3373720141914"},{"code":"WHO_002","displayName":"Họ và tên","attribute":"xBoLC0aruyJ","value":"NGUYỄN THỊ NUYÊN"},{"code":"WHO_003","displayName":"Giới tính","attribute":"rwreLO34Xg7","value":"02"},{"code":"WHO_004","displayName":"Năm sinh","attribute":"C7USC9MC8yH","value":"1959-01-01"},{"displayName":"Số CMT/CCCD","attribute":"ZQ93P672wQR","value":""},{"displayName":"Số điện thoại","attribute":"mZbgWADLTKY","value":""},{"code":"WHO_005","displayName":"Địa chỉ","attribute":"Bxp1Lhr8ZeN","value":""},{"code":"WHO_006","displayName":"Nghề nghiệp","attribute":"L4djJU4gMyb","value":""}]},{"orgUnit":"pfeCqgBS4Zb","trackedEntityType":"EL3fkeMR3xK","inactive":false,"deleted":false,"featureType":"NONE","programOwners":[],"enrollments":[{"orgUnit":"pfeCqgBS4Zb","program":"gPWs4FRX9dj","enrollmentDate":"2021-01-01","incidentDate":"2021-01-01","events":[]}],"relationships":[],"attributes":[{"code":"WHO_001","displayName":"Mã BHYT","attribute":"JHb1hzseNMg","value":"HT2373721005371"},{"code":"WHO_002","displayName":"Họ và tên","attribute":"xBoLC0aruyJ","value":"Phan Sỹ Cương"},{"code":"WHO_003","displayName":"Giới tính","attribute":"rwreLO34Xg7","value":"01"},{"code":"WHO_004","displayName":"Năm sinh","attribute":"C7USC9MC8yH","value":"1934-01-01"},{"displayName":"Số CMT/CCCD","attribute":"ZQ93P672wQR","value":""},{"displayName":"Số điện thoại","attribute":"mZbgWADLTKY","value":""},{"code":"WHO_005","displayName":"Địa chỉ","attribute":"Bxp1Lhr8ZeN","value":""},{"code":"WHO_006","displayName":"Nghề nghiệp","attribute":"L4djJU4gMyb","value":""}]},{"orgUnit":"pfeCqgBS4Zb","trackedEntityType":"EL3fkeMR3xK","inactive":false,"deleted":false,"featureType":"NONE","programOwners":[],"enrollments":[{"orgUnit":"pfeCqgBS4Zb","program":"gPWs4FRX9dj","enrollmentDate":"2021-01-01","incidentDate":"2021-01-01","events":[]}],"relationships":[],"attributes":[{"code":"WHO_001","displayName":"Mã BHYT","attribute":"JHb1hzseNMg","value":"BT2373720111960"},{"code":"WHO_002","displayName":"Họ và tên","attribute":"xBoLC0aruyJ","value":"PHẠM THỊ NGOẠT"},{"code":"WHO_003","displayName":"Giới tính","attribute":"rwreLO34Xg7","value":"02"},{"code":"WHO_004","displayName":"Năm sinh","attribute":"C7USC9MC8yH","value":"1932-01-01"},{"displayName":"Số CMT/CCCD","attribute":"ZQ93P672wQR","value":""},{"displayName":"Số điện thoại","attribute":"mZbgWADLTKY","value":""},{"code":"WHO_005","displayName":"Địa chỉ","attribute":"Bxp1Lhr8ZeN","value":""},{"code":"WHO_006","displayName":"Nghề nghiệp","attribute":"L4djJU4gMyb","value":""}]},{"orgUnit":"DaMOC6ucylB","trackedEntityType":"EL3fkeMR3xK","inactive":false,"deleted":false,"featureType":"NONE","programOwners":[],"enrollments":[{"orgUnit":"DaMOC6ucylB","program":"gPWs4FRX9dj","enrollmentDate":"2021-01-01","incidentDate":"2021-01-01","events":[]}],"relationships":[],"attributes":[{"code":"WHO_001","displayName":"Mã BHYT","attribute":"JHb1hzseNMg","value":"CK2373721092424"},{"code":"WHO_002","displayName":"Họ và tên","attribute":"xBoLC0aruyJ","value":"TRẦN THỊ KIỆM"},{"code":"WHO_003","displayName":"Giới tính","attribute":"rwreLO34Xg7","value":"02"},{"code":"WHO_004","displayName":"Năm sinh","attribute":"C7USC9MC8yH","value":"1932-01-01"},{"displayName":"Số CMT/CCCD","attribute":"ZQ93P672wQR","value":""},{"displayName":"Số điện thoại","attribute":"mZbgWADLTKY","value":""},{"code":"WHO_005","displayName":"Địa chỉ","attribute":"Bxp1Lhr8ZeN","value":""},{"code":"WHO_006","displayName":"Nghề nghiệp","attribute":"L4djJU4gMyb","value":""}]},{"orgUnit":"DaMOC6ucylB","trackedEntityType":"EL3fkeMR3xK","inactive":false,"deleted":false,"featureType":"NONE","programOwners":[],"enrollments":[{"orgUnit":"DaMOC6ucylB","program":"gPWs4FRX9dj","enrollmentDate":"2021-01-01","incidentDate":"2021-01-01","events":[]}],"relationships":[],"attributes":[{"code":"WHO_001","displayName":"Mã BHYT","attribute":"JHb1hzseNMg","value":"HT3372896015450"},{"code":"WHO_002","displayName":"Họ và tên","attribute":"xBoLC0aruyJ","value":"NGUYỄN THỊ THU"},{"code":"WHO_003","displayName":"Giới tính","attribute":"rwreLO34Xg7","value":"02"},{"code":"WHO_004","displayName":"Năm sinh","attribute":"C7USC9MC8yH","value":"1961-01-20"},{"displayName":"Số CMT/CCCD","attribute":"ZQ93P672wQR","value":""},{"displayName":"Số điện thoại","attribute":"mZbgWADLTKY","value":""},{"code":"WHO_005","displayName":"Địa chỉ","attribute":"Bxp1Lhr8ZeN","value":""},{"code":"WHO_006","displayName":"Nghề nghiệp","attribute":"L4djJU4gMyb","value":""}]},{"orgUnit":"UXpZHT2UPZ5","trackedEntityType":"EL3fkeMR3xK","inactive":false,"deleted":false,"featureType":"NONE","programOwners":[],"enrollments":[{"orgUnit":"UXpZHT2UPZ5","program":"gPWs4FRX9dj","enrollmentDate":"2021-01-01","incidentDate":"2021-01-01","events":[]}],"relationships":[],"attributes":[{"code":"WHO_001","displayName":"Mã BHYT","attribute":"JHb1hzseNMg","value":"CK2373721092281"},{"code":"WHO_002","displayName":"Họ và tên","attribute":"xBoLC0aruyJ","value":"ĐẶNG VĂN HẢI"},{"code":"WHO_003","displayName":"Giới tính","attribute":"rwreLO34Xg7","value":"01"},{"code":"WHO_004","displayName":"Năm sinh","attribute":"C7USC9MC8yH","value":"1952-08-20"},{"displayName":"Số CMT/CCCD","attribute":"ZQ93P672wQR","value":""},{"displayName":"Số điện thoại","attribute":"mZbgWADLTKY","value":""},{"code":"WHO_005","displayName":"Địa chỉ","attribute":"Bxp1Lhr8ZeN","value":""},{"code":"WHO_006","displayName":"Nghề nghiệp","attribute":"L4djJU4gMyb","value":""}]},{"orgUnit":"oqNqYhiiPkY","trackedEntityType":"EL3fkeMR3xK","inactive":false,"deleted":false,"featureType":"NONE","programOwners":[],"enrollments":[{"orgUnit":"oqNqYhiiPkY","program":"gPWs4FRX9dj","enrollmentDate":"2021-01-01","incidentDate":"2021-01-01","events":[]}],"relationships":[],"attributes":[{"code":"WHO_001","displayName":"Mã BHYT","attribute":"JHb1hzseNMg","value":"TS2373720468178"},{"code":"WHO_002","displayName":"Họ và tên","attribute":"xBoLC0aruyJ","value":"TẠ BÁ SỸ"},{"code":"WHO_003","displayName":"Giới tính","attribute":"rwreLO34Xg7","value":"01"},{"code":"WHO_004","displayName":"Năm sinh","attribute":"C7USC9MC8yH","value":"1963-09-01"},{"displayName":"Số CMT/CCCD","attribute":"ZQ93P672wQR","value":""},{"displayName":"Số điện thoại","attribute":"mZbgWADLTKY","value":""},{"code":"WHO_005","displayName":"Địa chỉ","attribute":"Bxp1Lhr8ZeN","value":""},{"code":"WHO_006","displayName":"Nghề nghiệp","attribute":"L4djJU4gMyb","value":""}]},{"orgUnit":"CItdVshvK3m","trackedEntityType":"EL3fkeMR3xK","inactive":false,"deleted":false,"featureType":"NONE","programOwners":[],"enrollments":[{"orgUnit":"CItdVshvK3m","program":"gPWs4FRX9dj","enrollmentDate":"2021-01-01","incidentDate":"2021-01-01","events":[]}],"relationships":[],"attributes":[{"code":"WHO_001","displayName":"Mã BHYT","attribute":"JHb1hzseNMg","value":"CN3373720595009"},{"code":"WHO_002","displayName":"Họ và tên","attribute":"xBoLC0aruyJ","value":"PHẠM XUÂN THỦY"},{"code":"WHO_003","displayName":"Giới tính","attribute":"rwreLO34Xg7","value":"01"},{"code":"WHO_004","displayName":"Năm sinh","attribute":"C7USC9MC8yH","value":"1954-01-01"},{"displayName":"Số CMT/CCCD","attribute":"ZQ93P672wQR","value":""},{"displayName":"Số điện thoại","attribute":"mZbgWADLTKY","value":""},{"code":"WHO_005","displayName":"Địa chỉ","attribute":"Bxp1Lhr8ZeN","value":""},{"code":"WHO_006","displayName":"Nghề nghiệp","attribute":"L4djJU4gMyb","value":""}]},{"orgUnit":"oqNqYhiiPkY","trackedEntityType":"EL3fkeMR3xK","inactive":false,"deleted":false,"featureType":"NONE","programOwners":[],"enrollments":[{"orgUnit":"oqNqYhiiPkY","program":"gPWs4FRX9dj","enrollmentDate":"2021-01-01","incidentDate":"2021-01-01","events":[]}],"relationships":[],"attributes":[{"code":"WHO_001","displayName":"Mã BHYT","attribute":"JHb1hzseNMg","value":"CN3373720468702"},{"code":"WHO_002","displayName":"Họ và tên","attribute":"xBoLC0aruyJ","value":"PHẠM THỊ MỪNG"},{"code":"WHO_003","displayName":"Giới tính","attribute":"rwreLO34Xg7","value":"02"},{"code":"WHO_004","displayName":"Năm sinh","attribute":"C7USC9MC8yH","value":"1958-01-01"},{"displayName":"Số CMT/CCCD","attribute":"ZQ93P672wQR","value":""},{"displayName":"Số điện thoại","attribute":"mZbgWADLTKY","value":""},{"code":"WHO_005","displayName":"Địa chỉ","attribute":"Bxp1Lhr8ZeN","value":""},{"code":"WHO_006","displayName":"Nghề nghiệp","attribute":"L4djJU4gMyb","value":""}]},{"orgUnit":"eLYrJDyRTX5","trackedEntityType":"EL3fkeMR3xK","inactive":false,"deleted":false,"featureType":"NONE","programOwners":[],"enrollments":[{"orgUnit":"eLYrJDyRTX5","program":"gPWs4FRX9dj","enrollmentDate":"2021-01-01","incidentDate":"2021-01-01","events":[]}],"relationships":[],"attributes":[{"code":"WHO_001","displayName":"Mã BHYT","attribute":"JHb1hzseNMg","value":"CN3373720593623"},{"code":"WHO_002","displayName":"Họ và tên","attribute":"xBoLC0aruyJ","value":"Lê Thị Duyên"},{"code":"WHO_003","displayName":"Giới tính","attribute":"rwreLO34Xg7","value":"02"},{"code":"WHO_004","displayName":"Năm sinh","attribute":"C7USC9MC8yH","value":"1959-01-01"},{"displayName":"Số CMT/CCCD","attribute":"ZQ93P672wQR","value":""},{"displayName":"Số điện thoại","attribute":"mZbgWADLTKY","value":""},{"code":"WHO_005","displayName":"Địa chỉ","attribute":"Bxp1Lhr8ZeN","value":""},{"code":"WHO_006","displayName":"Nghề nghiệp","attribute":"L4djJU4gMyb","value":""}]},{"orgUnit":"zwslFumJCg2","trackedEntityType":"EL3fkeMR3xK","inactive":false,"deleted":false,"featureType":"NONE","programOwners":[],"enrollments":[{"orgUnit":"zwslFumJCg2","program":"gPWs4FRX9dj","enrollmentDate":"2021-01-01","incidentDate":"2021-01-01","events":[]}],"relationships":[],"attributes":[{"code":"WHO_001","displayName":"Mã BHYT","attribute":"JHb1hzseNMg","value":"GB4373720092402"},{"code":"WHO_002","displayName":"Họ và tên","attribute":"xBoLC0aruyJ","value":"BÙI THỊ HÁN"},{"code":"WHO_003","displayName":"Giới tính","attribute":"rwreLO34Xg7","value":"02"},{"code":"WHO_004","displayName":"Năm sinh","attribute":"C7USC9MC8yH","value":"1965-01-01"},{"displayName":"Số CMT/CCCD","attribute":"ZQ93P672wQR","value":""},{"displayName":"Số điện thoại","attribute":"mZbgWADLTKY","value":""},{"code":"WHO_005","displayName":"Địa chỉ","attribute":"Bxp1Lhr8ZeN","value":""},{"code":"WHO_006","displayName":"Nghề nghiệp","attribute":"L4djJU4gMyb","value":""}]},{"orgUnit":"XeqMnv6PIoH","trackedEntityType":"EL3fkeMR3xK","inactive":false,"deleted":false,"featureType":"NONE","programOwners":[],"enrollments":[{"orgUnit":"XeqMnv6PIoH","program":"gPWs4FRX9dj","enrollmentDate":"2021-01-01","incidentDate":"2021-01-01","events":[]}],"relationships":[],"attributes":[{"code":"WHO_001","displayName":"Mã BHYT","attribute":"JHb1hzseNMg","value":"GB4373720020189"},{"code":"WHO_002","displayName":"Họ và tên","attribute":"xBoLC0aruyJ","value":"NGUYỄN THANH HỒNG"},{"code":"WHO_003","displayName":"Giới tính","attribute":"rwreLO34Xg7","value":"01"},{"code":"WHO_004","displayName":"Năm sinh","attribute":"C7USC9MC8yH","value":"1972-01-01"},{"displayName":"Số CMT/CCCD","attribute":"ZQ93P672wQR","value":""},{"displayName":"Số điện thoại","attribute":"mZbgWADLTKY","value":""},{"code":"WHO_005","displayName":"Địa chỉ","attribute":"Bxp1Lhr8ZeN","value":""},{"code":"WHO_006","displayName":"Nghề nghiệp","attribute":"L4djJU4gMyb","value":""}]},{"orgUnit":"pfeCqgBS4Zb","trackedEntityType":"EL3fkeMR3xK","inactive":false,"deleted":false,"featureType":"NONE","programOwners":[],"enrollments":[{"orgUnit":"pfeCqgBS4Zb","program":"gPWs4FRX9dj","enrollmentDate":"2021-01-01","incidentDate":"2021-01-01","events":[]}],"relationships":[],"attributes":[{"code":"WHO_001","displayName":"Mã BHYT","attribute":"JHb1hzseNMg","value":"GD4373720043223"},{"code":"WHO_002","displayName":"Họ và tên","attribute":"xBoLC0aruyJ","value":"NGUYỄN ĐÌNH LÂM"},{"code":"WHO_003","displayName":"Giới tính","attribute":"rwreLO34Xg7","value":"01"},{"code":"WHO_004","displayName":"Năm sinh","attribute":"C7USC9MC8yH","value":"1965-06-05"},{"displayName":"Số CMT/CCCD","attribute":"ZQ93P672wQR","value":""},{"displayName":"Số điện thoại","attribute":"mZbgWADLTKY","value":""},{"code":"WHO_005","displayName":"Địa chỉ","attribute":"Bxp1Lhr8ZeN","value":""},{"code":"WHO_006","displayName":"Nghề nghiệp","attribute":"L4djJU4gMyb","value":""}]},{"orgUnit":"AAfjzERP1rh","trackedEntityType":"EL3fkeMR3xK","inactive":false,"deleted":false,"featureType":"NONE","programOwners":[],"enrollments":[{"orgUnit":"AAfjzERP1rh","program":"gPWs4FRX9dj","enrollmentDate":"2021-01-01","incidentDate":"2021-01-01","events":[]}],"relationships":[],"attributes":[{"code":"WHO_001","displayName":"Mã BHYT","attribute":"JHb1hzseNMg","value":"GB4373720385315"},{"code":"WHO_002","displayName":"Họ và tên","attribute":"xBoLC0aruyJ","value":"LÊ VĂN LỤC"},{"code":"WHO_003","displayName":"Giới tính","attribute":"rwreLO34Xg7","value":"01"},{"code":"WHO_004","displayName":"Năm sinh","attribute":"C7USC9MC8yH","value":"1976-11-28"},{"displayName":"Số CMT/CCCD","attribute":"ZQ93P672wQR","value":""},{"displayName":"Số điện thoại","attribute":"mZbgWADLTKY","value":""},{"code":"WHO_005","displayName":"Địa chỉ","attribute":"Bxp1Lhr8ZeN","value":""},{"code":"WHO_006","displayName":"Nghề nghiệp","attribute":"L4djJU4gMyb","value":""}]},{"orgUnit":"eLYrJDyRTX5","trackedEntityType":"EL3fkeMR3xK","inactive":false,"deleted":false,"featureType":"NONE","programOwners":[],"enrollments":[{"orgUnit":"eLYrJDyRTX5","program":"gPWs4FRX9dj","enrollmentDate":"2021-01-01","incidentDate":"2021-01-01","events":[]}],"relationships":[],"attributes":[{"code":"WHO_001","displayName":"Mã BHYT","attribute":"JHb1hzseNMg","value":"GB4373720638068"},{"code":"WHO_002","displayName":"Họ và tên","attribute":"xBoLC0aruyJ","value":"LÊ VĂN TĨNH"},{"code":"WHO_003","displayName":"Giới tính","attribute":"rwreLO34Xg7","value":"01"},{"code":"WHO_004","displayName":"Năm sinh","attribute":"C7USC9MC8yH","value":"1963-01-01"},{"displayName":"Số CMT/CCCD","attribute":"ZQ93P672wQR","value":""},{"displayName":"Số điện thoại","attribute":"mZbgWADLTKY","value":""},{"code":"WHO_005","displayName":"Địa chỉ","attribute":"Bxp1Lhr8ZeN","value":""},{"code":"WHO_006","displayName":"Nghề nghiệp","attribute":"L4djJU4gMyb","value":""}]},{"orgUnit":"SpoPAZdJirm","trackedEntityType":"EL3fkeMR3xK","inactive":false,"deleted":false,"featureType":"NONE","programOwners":[],"enrollments":[{"orgUnit":"SpoPAZdJirm","program":"gPWs4FRX9dj","enrollmentDate":"2021-01-01","incidentDate":"2021-01-01","events":[]}],"relationships":[],"attributes":[{"code":"WHO_001","displayName":"Mã BHYT","attribute":"JHb1hzseNMg","value":"GD4373720010272"},{"code":"WHO_002","displayName":"Họ và tên","attribute":"xBoLC0aruyJ","value":"ĐINH THỊ HIỀN"},{"code":"WHO_003","displayName":"Giới tính","attribute":"rwreLO34Xg7","value":"02"},{"code":"WHO_004","displayName":"Năm sinh","attribute":"C7USC9MC8yH","value":"1959-09-25"},{"displayName":"Số CMT/CCCD","attribute":"ZQ93P672wQR","value":""},{"displayName":"Số điện thoại","attribute":"mZbgWADLTKY","value":""},{"code":"WHO_005","displayName":"Địa chỉ","attribute":"Bxp1Lhr8ZeN","value":""},{"code":"WHO_006","displayName":"Nghề nghiệp","attribute":"L4djJU4gMyb","value":""}]},{"orgUnit":"BAqlaZeQ8C3","trackedEntityType":"EL3fkeMR3xK","inactive":false,"deleted":false,"featureType":"NONE","programOwners":[],"enrollments":[{"orgUnit":"BAqlaZeQ8C3","program":"gPWs4FRX9dj","enrollmentDate":"2021-01-01","incidentDate":"2021-01-01","events":[]}],"relationships":[],"attributes":[{"code":"WHO_001","displayName":"Mã BHYT","attribute":"JHb1hzseNMg","value":"GB4373720581161"},{"code":"WHO_002","displayName":"Họ và tên","attribute":"xBoLC0aruyJ","value":"Lê Văn Cử"},{"code":"WHO_003","displayName":"Giới tính","attribute":"rwreLO34Xg7","value":"01"},{"code":"WHO_004","displayName":"Năm sinh","attribute":"C7USC9MC8yH","value":"1976-01-01"},{"displayName":"Số CMT/CCCD","attribute":"ZQ93P672wQR","value":""},{"displayName":"Số điện thoại","attribute":"mZbgWADLTKY","value":""},{"code":"WHO_005","displayName":"Địa chỉ","attribute":"Bxp1Lhr8ZeN","value":""},{"code":"WHO_006","displayName":"Nghề nghiệp","attribute":"L4djJU4gMyb","value":""}]},{"orgUnit":"t7cn9nU8Ait","trackedEntityType":"EL3fkeMR3xK","inactive":false,"deleted":false,"featureType":"NONE","programOwners":[],"enrollments":[{"orgUnit":"t7cn9nU8Ait","program":"gPWs4FRX9dj","enrollmentDate":"2021-01-01","incidentDate":"2021-01-01","events":[]}],"relationships":[],"attributes":[{"code":"WHO_001","displayName":"Mã BHYT","attribute":"JHb1hzseNMg","value":"GD4373721202329"},{"code":"WHO_002","displayName":"Họ và tên","attribute":"xBoLC0aruyJ","value":"PHẠM VĂN KHOA"},{"code":"WHO_003","displayName":"Giới tính","attribute":"rwreLO34Xg7","value":"01"},{"code":"WHO_004","displayName":"Năm sinh","attribute":"C7USC9MC8yH","value":"1960-07-14"},{"displayName":"Số CMT/CCCD","attribute":"ZQ93P672wQR","value":""},{"displayName":"Số điện thoại","attribute":"mZbgWADLTKY","value":""},{"code":"WHO_005","displayName":"Địa chỉ","attribute":"Bxp1Lhr8ZeN","value":""},{"code":"WHO_006","displayName":"Nghề nghiệp","attribute":"L4djJU4gMyb","value":""}]},{"orgUnit":"rkvNtzZNwsG","trackedEntityType":"EL3fkeMR3xK","inactive":false,"deleted":false,"featureType":"NONE","programOwners":[],"enrollments":[{"orgUnit":"rkvNtzZNwsG","program":"gPWs4FRX9dj","enrollmentDate":"2021-01-01","incidentDate":"2021-01-01","events":[]}],"relationships":[],"attributes":[{"code":"WHO_001","displayName":"Mã BHYT","attribute":"JHb1hzseNMg","value":"GD4373720062524"},{"code":"WHO_002","displayName":"Họ và tên","attribute":"xBoLC0aruyJ","value":"ĐẶNG THỊ CÚC"},{"code":"WHO_003","displayName":"Giới tính","attribute":"rwreLO34Xg7","value":"02"},{"code":"WHO_004","displayName":"Năm sinh","attribute":"C7USC9MC8yH","value":"1972-01-20"},{"displayName":"Số CMT/CCCD","attribute":"ZQ93P672wQR","value":""},{"displayName":"Số điện thoại","attribute":"mZbgWADLTKY","value":""},{"code":"WHO_005","displayName":"Địa chỉ","attribute":"Bxp1Lhr8ZeN","value":""},{"code":"WHO_006","displayName":"Nghề nghiệp","attribute":"L4djJU4gMyb","value":""}]},{"orgUnit":"Qm1BytbwrhI","trackedEntityType":"EL3fkeMR3xK","inactive":false,"deleted":false,"featureType":"NONE","programOwners":[],"enrollments":[{"orgUnit":"Qm1BytbwrhI","program":"gPWs4FRX9dj","enrollmentDate":"2021-01-01","incidentDate":"2021-01-01","events":[]}],"relationships":[],"attributes":[{"code":"WHO_001","displayName":"Mã BHYT","attribute":"JHb1hzseNMg","value":"GD4373720079213"},{"code":"WHO_002","displayName":"Họ và tên","attribute":"xBoLC0aruyJ","value":"Phạm Văn Lục"},{"code":"WHO_003","displayName":"Giới tính","attribute":"rwreLO34Xg7","value":"01"},{"code":"WHO_004","displayName":"Năm sinh","attribute":"C7USC9MC8yH","value":"1962-10-20"},{"displayName":"Số CMT/CCCD","attribute":"ZQ93P672wQR","value":""},{"displayName":"Số điện thoại","attribute":"mZbgWADLTKY","value":""},{"code":"WHO_005","displayName":"Địa chỉ","attribute":"Bxp1Lhr8ZeN","value":""},{"code":"WHO_006","displayName":"Nghề nghiệp","attribute":"L4djJU4gMyb","value":""}]},{"orgUnit":"BAqlaZeQ8C3","trackedEntityType":"EL3fkeMR3xK","inactive":false,"deleted":false,"featureType":"NONE","programOwners":[],"enrollments":[{"orgUnit":"BAqlaZeQ8C3","program":"gPWs4FRX9dj","enrollmentDate":"2021-01-01","incidentDate":"2021-01-01","events":[]}],"relationships":[],"attributes":[{"code":"WHO_001","displayName":"Mã BHYT","attribute":"JHb1hzseNMg","value":"GB4373720558591"},{"code":"WHO_002","displayName":"Họ và tên","attribute":"xBoLC0aruyJ","value":"ĐỖ VĂN TRÁI"},{"code":"WHO_003","displayName":"Giới tính","attribute":"rwreLO34Xg7","value":"01"},{"code":"WHO_004","displayName":"Năm sinh","attribute":"C7USC9MC8yH","value":"1956-01-01"},{"displayName":"Số CMT/CCCD","attribute":"ZQ93P672wQR","value":""},{"displayName":"Số điện thoại","attribute":"mZbgWADLTKY","value":""},{"code":"WHO_005","displayName":"Địa chỉ","attribute":"Bxp1Lhr8ZeN","value":""},{"code":"WHO_006","displayName":"Nghề nghiệp","attribute":"L4djJU4gMyb","value":""}]},{"orgUnit":"rkvNtzZNwsG","trackedEntityType":"EL3fkeMR3xK","inactive":false,"deleted":false,"featureType":"NONE","programOwners":[],"enrollments":[{"orgUnit":"rkvNtzZNwsG","program":"gPWs4FRX9dj","enrollmentDate":"2021-01-01","incidentDate":"2021-01-01","events":[]}],"relationships":[],"attributes":[{"code":"WHO_001","displayName":"Mã BHYT","attribute":"JHb1hzseNMg","value":"GD4373721265953"},{"code":"WHO_002","displayName":"Họ và tên","attribute":"xBoLC0aruyJ","value":"Đặng Văn Kế"},{"code":"WHO_003","displayName":"Giới tính","attribute":"rwreLO34Xg7","value":"01"},{"code":"WHO_004","displayName":"Năm sinh","attribute":"C7USC9MC8yH","value":"1953-01-01"},{"displayName":"Số CMT/CCCD","attribute":"ZQ93P672wQR","value":""},{"displayName":"Số điện thoại","attribute":"mZbgWADLTKY","value":""},{"code":"WHO_005","displayName":"Địa chỉ","attribute":"Bxp1Lhr8ZeN","value":""},{"code":"WHO_006","displayName":"Nghề nghiệp","attribute":"L4djJU4gMyb","value":""}]},{"orgUnit":"Qm1BytbwrhI","trackedEntityType":"EL3fkeMR3xK","inactive":false,"deleted":false,"featureType":"NONE","programOwners":[],"enrollments":[{"orgUnit":"Qm1BytbwrhI","program":"gPWs4FRX9dj","enrollmentDate":"2021-01-01","incidentDate":"2021-01-01","events":[]}],"relationships":[],"attributes":[{"code":"WHO_001","displayName":"Mã BHYT","attribute":"JHb1hzseNMg","value":"GD4373720019424"},{"code":"WHO_002","displayName":"Họ và tên","attribute":"xBoLC0aruyJ","value":"Vũ Văn Lượng"},{"code":"WHO_003","displayName":"Giới tính","attribute":"rwreLO34Xg7","value":"01"},{"code":"WHO_004","displayName":"Năm sinh","attribute":"C7USC9MC8yH","value":"1957-01-01"},{"displayName":"Số CMT/CCCD","attribute":"ZQ93P672wQR","value":""},{"displayName":"Số điện thoại","attribute":"mZbgWADLTKY","value":""},{"code":"WHO_005","displayName":"Địa chỉ","attribute":"Bxp1Lhr8ZeN","value":""},{"code":"WHO_006","displayName":"Nghề nghiệp","attribute":"L4djJU4gMyb","value":""}]},{"orgUnit":"t7cn9nU8Ait","trackedEntityType":"EL3fkeMR3xK","inactive":false,"deleted":false,"featureType":"NONE","programOwners":[],"enrollments":[{"orgUnit":"t7cn9nU8Ait","program":"gPWs4FRX9dj","enrollmentDate":"2021-01-01","incidentDate":"2021-01-01","events":[]}],"relationships":[],"attributes":[{"code":"WHO_001","displayName":"Mã BHYT","attribute":"JHb1hzseNMg","value":"GD4372797067668"},{"code":"WHO_002","displayName":"Họ và tên","attribute":"xBoLC0aruyJ","value":"NGUYỄN VĂN THẮNG"},{"code":"WHO_003","displayName":"Giới tính","attribute":"rwreLO34Xg7","value":"01"},{"code":"WHO_004","displayName":"Năm sinh","attribute":"C7USC9MC8yH","value":"1969-08-09"},{"displayName":"Số CMT/CCCD","attribute":"ZQ93P672wQR","value":""},{"displayName":"Số điện thoại","attribute":"mZbgWADLTKY","value":""},{"code":"WHO_005","displayName":"Địa chỉ","attribute":"Bxp1Lhr8ZeN","value":""},{"code":"WHO_006","displayName":"Nghề nghiệp","attribute":"L4djJU4gMyb","value":""}]},{"orgUnit":"n1YBaV10Wlz","trackedEntityType":"EL3fkeMR3xK","inactive":false,"deleted":false,"featureType":"NONE","programOwners":[],"enrollments":[{"orgUnit":"n1YBaV10Wlz","program":"gPWs4FRX9dj","enrollmentDate":"2021-01-01","incidentDate":"2021-01-01","events":[]}],"relationships":[],"attributes":[{"code":"WHO_001","displayName":"Mã BHYT","attribute":"JHb1hzseNMg","value":"HT3372896030155"},{"code":"WHO_002","displayName":"Họ và tên","attribute":"xBoLC0aruyJ","value":"TRỊNH PHÚ SƠN"},{"code":"WHO_003","displayName":"Giới tính","attribute":"rwreLO34Xg7","value":"01"},{"code":"WHO_004","displayName":"Năm sinh","attribute":"C7USC9MC8yH","value":"1953-01-01"},{"displayName":"Số CMT/CCCD","attribute":"ZQ93P672wQR","value":""},{"displayName":"Số điện thoại","attribute":"mZbgWADLTKY","value":""},{"code":"WHO_005","displayName":"Địa chỉ","attribute":"Bxp1Lhr8ZeN","value":""},{"code":"WHO_006","displayName":"Nghề nghiệp","attribute":"L4djJU4gMyb","value":""}]},{"orgUnit":"Gr12HuYTV7f","trackedEntityType":"EL3fkeMR3xK","inactive":false,"deleted":false,"featureType":"NONE","programOwners":[],"enrollments":[{"orgUnit":"Gr12HuYTV7f","program":"gPWs4FRX9dj","enrollmentDate":"2021-01-01","incidentDate":"2021-01-01","events":[]}],"relationships":[],"attributes":[{"code":"WHO_001","displayName":"Mã BHYT","attribute":"JHb1hzseNMg","value":"CK2373721115331"},{"code":"WHO_002","displayName":"Họ và tên","attribute":"xBoLC0aruyJ","value":"BÙI XUÂN CHINH"},{"code":"WHO_003","displayName":"Giới tính","attribute":"rwreLO34Xg7","value":"01"},{"code":"WHO_004","displayName":"Năm sinh","attribute":"C7USC9MC8yH","value":"1940-01-01"},{"displayName":"Số CMT/CCCD","attribute":"ZQ93P672wQR","value":""},{"displayName":"Số điện thoại","attribute":"mZbgWADLTKY","value":""},{"code":"WHO_005","displayName":"Địa chỉ","attribute":"Bxp1Lhr8ZeN","value":""},{"code":"WHO_006","displayName":"Nghề nghiệp","attribute":"L4djJU4gMyb","value":""}]},{"orgUnit":"Gr12HuYTV7f","trackedEntityType":"EL3fkeMR3xK","inactive":false,"deleted":false,"featureType":"NONE","programOwners":[],"enrollments":[{"orgUnit":"Gr12HuYTV7f","program":"gPWs4FRX9dj","enrollmentDate":"2021-01-01","incidentDate":"2021-01-01","events":[]}],"relationships":[],"attributes":[{"code":"WHO_001","displayName":"Mã BHYT","attribute":"JHb1hzseNMg","value":"HT2373721011673"},{"code":"WHO_002","displayName":"Họ và tên","attribute":"xBoLC0aruyJ","value":"MAI THỊ TIỆN"},{"code":"WHO_003","displayName":"Giới tính","attribute":"rwreLO34Xg7","value":"02"},{"code":"WHO_004","displayName":"Năm sinh","attribute":"C7USC9MC8yH","value":"1942-01-01"},{"displayName":"Số CMT/CCCD","attribute":"ZQ93P672wQR","value":""},{"displayName":"Số điện thoại","attribute":"mZbgWADLTKY","value":""},{"code":"WHO_005","displayName":"Địa chỉ","attribute":"Bxp1Lhr8ZeN","value":""},{"code":"WHO_006","displayName":"Nghề nghiệp","attribute":"L4djJU4gMyb","value":""}]},{"orgUnit":"zwslFumJCg2","trackedEntityType":"EL3fkeMR3xK","inactive":false,"deleted":false,"featureType":"NONE","programOwners":[],"enrollments":[{"orgUnit":"zwslFumJCg2","program":"gPWs4FRX9dj","enrollmentDate":"2021-01-01","incidentDate":"2021-01-01","events":[]}],"relationships":[],"attributes":[{"code":"WHO_001","displayName":"Mã BHYT","attribute":"JHb1hzseNMg","value":"GB4373720076677"},{"code":"WHO_002","displayName":"Họ và tên","attribute":"xBoLC0aruyJ","value":"NGUYỄN ĐÌNH LONG"},{"code":"WHO_003","displayName":"Giới tính","attribute":"rwreLO34Xg7","value":"01"},{"code":"WHO_004","displayName":"Năm sinh","attribute":"C7USC9MC8yH","value":"1991-08-20"},{"displayName":"Số CMT/CCCD","attribute":"ZQ93P672wQR","value":""},{"displayName":"Số điện thoại","attribute":"mZbgWADLTKY","value":""},{"code":"WHO_005","displayName":"Địa chỉ","attribute":"Bxp1Lhr8ZeN","value":""},{"code":"WHO_006","displayName":"Nghề nghiệp","attribute":"L4djJU4gMyb","value":""}]},{"orgUnit":"oqNqYhiiPkY","trackedEntityType":"EL3fkeMR3xK","inactive":false,"deleted":false,"featureType":"NONE","programOwners":[],"enrollments":[{"orgUnit":"oqNqYhiiPkY","program":"gPWs4FRX9dj","enrollmentDate":"2021-01-01","incidentDate":"2021-01-01","events":[]}],"relationships":[],"attributes":[{"code":"WHO_001","displayName":"Mã BHYT","attribute":"JHb1hzseNMg","value":"GD4373720499423"},{"code":"WHO_002","displayName":"Họ và tên","attribute":"xBoLC0aruyJ","value":"Tạ Văn Luật"},{"code":"WHO_003","displayName":"Giới tính","attribute":"rwreLO34Xg7","value":"01"},{"code":"WHO_004","displayName":"Năm sinh","attribute":"C7USC9MC8yH","value":"1977-01-01"},{"displayName":"Số CMT/CCCD","attribute":"ZQ93P672wQR","value":""},{"displayName":"Số điện thoại","attribute":"mZbgWADLTKY","value":""},{"code":"WHO_005","displayName":"Địa chỉ","attribute":"Bxp1Lhr8ZeN","value":""},{"code":"WHO_006","displayName":"Nghề nghiệp","attribute":"L4djJU4gMyb","value":""}]},{"orgUnit":"Qm1BytbwrhI","trackedEntityType":"EL3fkeMR3xK","inactive":false,"deleted":false,"featureType":"NONE","programOwners":[],"enrollments":[{"orgUnit":"Qm1BytbwrhI","program":"gPWs4FRX9dj","enrollmentDate":"2021-01-01","incidentDate":"2021-01-01","events":[]}],"relationships":[],"attributes":[{"code":"WHO_001","displayName":"Mã BHYT","attribute":"JHb1hzseNMg","value":"GD4373720101886"},{"code":"WHO_002","displayName":"Họ và tên","attribute":"xBoLC0aruyJ","value":"VŨ VĂN VĨNH"},{"code":"WHO_003","displayName":"Giới tính","attribute":"rwreLO34Xg7","value":"01"},{"code":"WHO_004","displayName":"Năm sinh","attribute":"C7USC9MC8yH","value":"1963-01-01"},{"displayName":"Số CMT/CCCD","attribute":"ZQ93P672wQR","value":""},{"displayName":"Số điện thoại","attribute":"mZbgWADLTKY","value":""},{"code":"WHO_005","displayName":"Địa chỉ","attribute":"Bxp1Lhr8ZeN","value":""},{"code":"WHO_006","displayName":"Nghề nghiệp","attribute":"L4djJU4gMyb","value":""}]}]}