{
    "categories": [
        {
            "code": "default",
            "created": "2021-04-29T03:07:13.983",
            "lastUpdated": "2021-07-31T20:59:53.113",
            "name": "default",
            "id": "GLevLNI9wkl",
            "dataDimensionType": "DISAGGREGATION",
            "publicAccess": "rw------",
            "dataDimension": false,
            "userGroupAccesses": [],
            "attributeValues": [],
            "translations": [],
            "userAccesses": [],
            "categoryOptions": [
                {
                    "id": "xYerKDKCefk"
                }
            ]
        },
        {
            "created": "2018-04-29T16:45:24.783",
            "lastUpdated": "2021-05-02T09:07:19.214",
            "name": "Giới tính",
            "id": "xh9C7doe5wo",
            "dataDimensionType": "DISAGGREGATION",
            "publicAccess": "rw------",
            "dataDimension": true,
            "lastUpdatedBy": {
                "displayName": "P2ild Dev",
                "id": "RBqxIBCBcAO",
                "username": "duylp"
            },
            "user": {
                "code": "admin",
                "displayName": "admin admin",
                "id": "M5zQapPyTZI",
                "username": "admin"
            },
            "userGroupAccesses": [],
            "attributeValues": [],
            "translations": [
                {
                    "property": "SHORT_NAME",
                    "locale": "vi",
                    "value": "Giới"
                },
                {
                    "property": "NAME",
                    "locale": "vi",
                    "value": "Giới"
                }
            ],
            "userAccesses": [],
            "categoryOptions": [
                {
                    "id": "puIm9IHVNY8"
                },
                {
                    "id": "iFsvA6tMlko"
                }
            ]
        }
    ]
}