{"programStageSections":[{"created":"2021-08-25T08:33:18.849","lastUpdated":"2021-08-25T08:33:18.849","name":"Chẩn đoán và điều trị","id":"TgUnsWmMh1o","sortOrder":2,"renderType":{"MOBILE":{"type":"LISTING"},"DESKTOP":{"type":"LISTING"}},"lastUpdatedBy":{"displayName":"Mai Thanh ","id":"qVzRJmKGpzz","username":"maint"},"programStage":{"id":"WeA1NcfqeyZ"},"programIndicators":[],"translations":[],"dataElements":[{"id":"udwtZvJMnVL"},{"id":"dqT5ZDL27U4"},{"id":"mVdtFRM2gFX"},{"id":"mOguWgQg1or"}]},{"created":"2021-08-25T08:44:27.226","lastUpdated":"2021-08-25T08:46:34.052","name":"Chẩn đoán và điều trị","id":"fZ0ZpN6vIH8","sortOrder":2,"renderType":{"MOBILE":{"type":"LISTING"},"DESKTOP":{"type":"LISTING"}},"lastUpdatedBy":{"displayName":"Mai Thanh ","id":"qVzRJmKGpzz","username":"maint"},"programStage":{"id":"zb4274oHwSq"},"programIndicators":[],"translations":[],"dataElements":[{"id":"udwtZvJMnVL"},{"id":"kuc11Gzf1Ln"},{"id":"mVdtFRM2gFX"},{"id":"mOguWgQg1or"}]},{"created":"2021-05-19T08:37:34.752","lastUpdated":"2021-08-25T08:46:34.051","name":"Thông tin bệnh","id":"vbQ5eGDP7tI","sortOrder":0,"renderType":{"MOBILE":{"type":"LISTING"},"DESKTOP":{"type":"LISTING"}},"lastUpdatedBy":{"displayName":"Mai Thanh ","id":"qVzRJmKGpzz","username":"maint"},"programStage":{"id":"zb4274oHwSq"},"programIndicators":[],"translations":[],"dataElements":[{"id":"iXw1Eq7HqjS"},{"id":"iedBhc5hNku"},{"id":"vig6FKWLnu7"},{"id":"G7CZ83GipKS"},{"id":"oXwh2J3F8ql"},{"id":"mfqPfxGZ8c8"},{"id":"G6kqlsUyuQe"},{"id":"vVs8M3PXMX1"},{"id":"RKGwWCwiHWO"},{"id":"MOWvMDpDCpb"},{"id":"KFQhr1CkqQK"},{"id":"XdlRaZg07oS"},{"id":"fKw40qHnwbR"},{"id":"X0kBm02Gyft"},{"id":"hfGTym6BfK1"}]},{"created":"2021-05-05T07:56:07.331","lastUpdated":"2021-08-25T08:33:19.306","name":"Tình trạng bệnh","id":"YadUBND1UZd","sortOrder":0,"renderType":{"MOBILE":{"type":"LISTING"},"DESKTOP":{"type":"LISTING"}},"lastUpdatedBy":{"displayName":"Mai Thanh ","id":"qVzRJmKGpzz","username":"maint"},"programStage":{"id":"WeA1NcfqeyZ"},"programIndicators":[],"translations":[],"dataElements":[{"id":"iXw1Eq7HqjS"},{"id":"iedBhc5hNku"},{"id":"vig6FKWLnu7"},{"id":"G7CZ83GipKS"},{"id":"oXwh2J3F8ql"},{"id":"mfqPfxGZ8c8"},{"id":"G6kqlsUyuQe"},{"id":"vVs8M3PXMX1"},{"id":"RKGwWCwiHWO"},{"id":"IBFOL0bTZoY"},{"id":"KFQhr1CkqQK"},{"id":"X0kBm02Gyft"},{"id":"hfGTym6BfK1"},{"id":"VPFntPj8o3W"}]},{"created":"2021-05-20T10:49:55.470","lastUpdated":"2021-08-25T08:33:19.306","name":"Xét nghiệm","id":"CZ3pQuidBmb","sortOrder":1,"renderType":{"MOBILE":{"type":"LISTING"},"DESKTOP":{"type":"LISTING"}},"lastUpdatedBy":{"displayName":"Mai Thanh ","id":"qVzRJmKGpzz","username":"maint"},"programStage":{"id":"WeA1NcfqeyZ"},"programIndicators":[],"translations":[],"dataElements":[{"id":"ndg4B889111"},{"id":"X1sJxFHNvWO"},{"id":"UiodmaCcmH5"},{"id":"jWBytWfQ6uo"}]},{"created":"2021-05-19T08:37:34.753","lastUpdated":"2021-08-25T08:46:34.052","name":"Xét nghiệm","id":"LElHEtFAAjO","sortOrder":1,"renderType":{"MOBILE":{"type":"LISTING"},"DESKTOP":{"type":"LISTING"}},"lastUpdatedBy":{"displayName":"Mai Thanh ","id":"qVzRJmKGpzz","username":"maint"},"programStage":{"id":"zb4274oHwSq"},"programIndicators":[],"translations":[],"dataElements":[{"id":"ueYR0Cp6V7D"},{"id":"ZPPVAD13Evr"},{"id":"ndg4B889111"},{"id":"X1sJxFHNvWO"},{"id":"UiodmaCcmH5"},{"id":"jWBytWfQ6uo"}]}]}